{
  "updatedAt": "2026-06-27T21:45:15.324Z",
  "source": "github-actions",
  "totalValue": 15899.090249423187,
  "cashValue": 13721.42807061,
  "cashPct": 86.30322776554972,
  "dataAgeMinutes": 0,
  "isStale": false,
  "isDataBlocked": false,
  "weights": {
    "USDT": 76.85272621981183,
    "USDGO": 9.450501545737888,
    "BTC": 6.977447239861707,
    "ETH": 1.5811973958391772,
    "DOGE": 2.3805801306967957,
    "BGB": 0.2679580402464387,
    "VOO": 0,
    "XAUT": 0,
    "AVGO": 0,
    "FN": 0,
    "MU": 1.266619638556401,
    "SNDK": 0,
    "DRAM": 0,
    "WDC": 1.2229697892497606,
    "ASX": 0,
    "AAOI": 0,
    "GLW": 0
  },
  "priceErrors": {},
  "positions": [
    {
      "symbol": "USDT",
      "name": "Tether",
      "type": "cash",
      "quantity": 12218.88430083,
      "cost": 1,
      "price": 1,
      "priceOk": true,
      "priceSource": "Fixed 1 USDT",
      "priceUpdatedAt": "2026-06-27T21:45:14.974Z",
      "priceError": null,
      "dataAgeMinutes": 0,
      "isStale": false,
      "isDataBlocked": false,
      "value": 12218.88430083,
      "pnl": 0,
      "pnlPct": 0,
      "weightPct": 76.85272621981183
    },
    {
      "symbol": "USDGO",
      "name": "USDGO",
      "type": "cash",
      "quantity": 1502.54376978,
      "cost": 1.0019,
      "price": 1,
      "priceOk": true,
      "priceSource": "Fixed 1 USDT",
      "priceUpdatedAt": "2026-06-27T21:45:14.975Z",
      "priceError": null,
      "dataAgeMinutes": 0,
      "isStale": false,
      "isDataBlocked": false,
      "value": 1502.54376978,
      "pnl": -2.8548331625820538,
      "pnlPct": -0.18963968459926497,
      "weightPct": 9.450501545737888
    },
    {
      "symbol": "BTC",
      "name": "Bitcoin",
      "type": "crypto",
      "quantity": 0.01841215,
      "cost": 59741.49,
      "price": 60251.01,
      "priceOk": true,
      "priceSource": "Bitget BTCUSDT",
      "priceUpdatedAt": "2026-06-27T21:45:14.975Z",
      "priceError": null,
      "dataAgeMinutes": 0,
      "isStale": false,
      "isDataBlocked": false,
      "value": 1109.3506337715,
      "pnl": 9.381358668000075,
      "pnlPct": 0.8528746102583048,
      "weightPct": 6.977447239861707
    },
    {
      "symbol": "ETH",
      "name": "Ethereum",
      "type": "crypto",
      "quantity": 0.1592747,
      "cost": 1569.49,
      "price": 1578.38,
      "priceOk": true,
      "priceSource": "Bitget ETHUSDT",
      "priceUpdatedAt": "2026-06-27T21:45:15.040Z",
      "priceError": null,
      "dataAgeMinutes": 0,
      "isStale": false,
      "isDataBlocked": false,
      "value": 251.396000986,
      "pnl": 1.4159520830000076,
      "pnlPct": 0.5664260364831919,
      "weightPct": 1.5811973958391772
    },
    {
      "symbol": "DOGE",
      "name": "Dogecoin",
      "type": "crypto",
      "quantity": 5073.6003142,
      "cost": 0.07489,
      "price": 0.0746,
      "priceOk": true,
      "priceSource": "Bitget DOGEUSDT",
      "priceUpdatedAt": "2026-06-27T21:45:15.041Z",
      "priceError": null,
      "dataAgeMinutes": 0,
      "isStale": false,
      "isDataBlocked": false,
      "value": 378.49058343932,
      "pnl": -1.4713440911179987,
      "pnlPct": -0.38723461076245125,
      "weightPct": 2.3805801306967957
    },
    {
      "symbol": "BGB",
      "name": "Bitget Token",
      "type": "crypto",
      "quantity": 25.91259087,
      "cost": 1.978,
      "price": 1.6441,
      "priceOk": true,
      "priceSource": "Bitget BGBUSDT",
      "priceUpdatedAt": "2026-06-27T21:45:15.042Z",
      "priceError": null,
      "dataAgeMinutes": 0,
      "isStale": false,
      "isDataBlocked": false,
      "value": 42.602890649367,
      "pnl": -8.652214091493,
      "pnlPct": -16.88068756319515,
      "weightPct": 0.2679580402464387
    },
    {
      "symbol": "VOO",
      "name": "Vanguard S&P 500 ETF",
      "type": "watch",
      "quantity": 0,
      "cost": 0,
      "price": 672.25,
      "priceOk": true,
      "priceSource": "Bitget RVOOUSDT",
      "priceUpdatedAt": "2026-06-27T21:45:15.043Z",
      "priceError": null,
      "dataAgeMinutes": 0,
      "isStale": false,
      "isDataBlocked": false,
      "value": 0,
      "pnl": 0,
      "pnlPct": 0,
      "weightPct": 0
    },
    {
      "symbol": "XAUT",
      "name": "Tether Gold",
      "type": "watch",
      "quantity": 0,
      "cost": 0,
      "price": 4072.34,
      "priceOk": true,
      "priceSource": "Bitget XAUTUSDT",
      "priceUpdatedAt": "2026-06-27T21:45:15.044Z",
      "priceError": null,
      "dataAgeMinutes": 0,
      "isStale": false,
      "isDataBlocked": false,
      "value": 0,
      "pnl": 0,
      "pnlPct": 0,
      "weightPct": 0
    },
    {
      "symbol": "AVGO",
      "name": "Broadcom",
      "type": "watch",
      "quantity": 0,
      "cost": 0,
      "price": 365.75,
      "priceOk": true,
      "priceSource": "Bitget RAVGOUSDT",
      "priceUpdatedAt": "2026-06-27T21:45:15.045Z",
      "priceError": null,
      "dataAgeMinutes": 0,
      "isStale": false,
      "isDataBlocked": false,
      "value": 0,
      "pnl": 0,
      "pnlPct": 0,
      "weightPct": 0
    },
    {
      "symbol": "FN",
      "name": "Fabrinet",
      "type": "watch",
      "quantity": 0,
      "cost": 0,
      "price": 523.4,
      "priceOk": true,
      "priceSource": "Bitget RFNUSDT",
      "priceUpdatedAt": "2026-06-27T21:45:15.045Z",
      "priceError": null,
      "dataAgeMinutes": 0,
      "isStale": false,
      "isDataBlocked": false,
      "value": 0,
      "pnl": 0,
      "pnlPct": 0,
      "weightPct": 0
    },
    {
      "symbol": "MU",
      "name": "Micron",
      "type": "watch",
      "quantity": 0.17540371,
      "cost": 1139.16,
      "price": 1148.1,
      "priceOk": true,
      "priceSource": "Bitget RMUUSDT",
      "priceUpdatedAt": "2026-06-27T21:45:15.046Z",
      "priceError": null,
      "dataAgeMinutes": 0,
      "isStale": false,
      "isDataBlocked": false,
      "value": 201.38099945099998,
      "pnl": 1.5681091673999674,
      "pnlPct": 0.7847887917412666,
      "weightPct": 1.266619638556401
    },
    {
      "symbol": "SNDK",
      "name": "SanDisk",
      "type": "watch",
      "quantity": 0,
      "cost": 0,
      "price": 2106.02,
      "priceOk": true,
      "priceSource": "Bitget RSNDKUSDT",
      "priceUpdatedAt": "2026-06-27T21:45:15.047Z",
      "priceError": null,
      "dataAgeMinutes": 0,
      "isStale": false,
      "isDataBlocked": false,
      "value": 0,
      "pnl": 0,
      "pnlPct": 0,
      "weightPct": 0
    },
    {
      "symbol": "DRAM",
      "name": "Roundhill Memory ETF",
      "type": "watch",
      "quantity": 0,
      "cost": 0,
      "price": 72.08,
      "priceOk": true,
      "priceSource": "Bitget RDRAMUSDT",
      "priceUpdatedAt": "2026-06-27T21:45:15.048Z",
      "priceError": null,
      "dataAgeMinutes": 0,
      "isStale": false,
      "isDataBlocked": false,
      "value": 0,
      "pnl": 0,
      "pnlPct": 0,
      "weightPct": 0
    },
    {
      "symbol": "WDC",
      "name": "Western Digital",
      "type": "watch",
      "quantity": 0.3305247,
      "cost": 604.3,
      "price": 588.28,
      "priceOk": true,
      "priceSource": "Bitget RWDCUSDT",
      "priceUpdatedAt": "2026-06-27T21:45:15.049Z",
      "priceError": null,
      "dataAgeMinutes": 0,
      "isStale": false,
      "isDataBlocked": false,
      "value": 194.441070516,
      "pnl": -5.295005693999997,
      "pnlPct": -2.651001158365049,
      "weightPct": 1.2229697892497606
    },
    {
      "symbol": "ASX",
      "name": "ASE Technology",
      "type": "watch",
      "quantity": 0,
      "cost": 0,
      "price": 39.87,
      "priceOk": true,
      "priceSource": "Bitget RASXUSDT",
      "priceUpdatedAt": "2026-06-27T21:45:15.049Z",
      "priceError": null,
      "dataAgeMinutes": 0,
      "isStale": false,
      "isDataBlocked": false,
      "value": 0,
      "pnl": 0,
      "pnlPct": 0,
      "weightPct": 0
    },
    {
      "symbol": "AAOI",
      "name": "Applied Optoelectronics",
      "type": "watch",
      "quantity": 0,
      "cost": 0,
      "price": 134.46,
      "priceOk": true,
      "priceSource": "Bitget RAAOIUSDT",
      "priceUpdatedAt": "2026-06-27T21:45:15.050Z",
      "priceError": null,
      "dataAgeMinutes": 0,
      "isStale": false,
      "isDataBlocked": false,
      "value": 0,
      "pnl": 0,
      "pnlPct": 0,
      "weightPct": 0
    },
    {
      "symbol": "GLW",
      "name": "Corning",
      "type": "watch",
      "quantity": 0,
      "cost": 0,
      "price": 220.14,
      "priceOk": true,
      "priceSource": "Bitget RGLWUSDT",
      "priceUpdatedAt": "2026-06-27T21:45:15.051Z",
      "priceError": null,
      "dataAgeMinutes": 0,
      "isStale": false,
      "isDataBlocked": false,
      "value": 0,
      "pnl": 0,
      "pnlPct": 0,
      "weightPct": 0
    }
  ],
  "btcFiveMinuteChangePct": 0.000016597513131599305,
  "highWatermark": 15923.477929634584,
  "drawdownPct": 0.15315548725702893,
  "btcWeeklyGainPct": -0.1797231885159996,
  "buyPauseUntil": null,
  "buyPaused": false
}
