{
  "updatedAt": "2026-07-01T08:55:15.227Z",
  "source": "github-actions",
  "totalValue": 15786.969399912557,
  "cashValue": 7004.822359649999,
  "cashPct": 44.37091237846321,
  "dataAgeMinutes": 0,
  "isStale": false,
  "isDataBlocked": false,
  "weights": {
    "USDT": 34.84586178079543,
    "USDGO": 9.525050597667775,
    "BTC": 9.575577763952422,
    "ETH": 2.543912712089151,
    "DOGE": 3.579919245442627,
    "BGB": 0.2638207894770588,
    "CRCL": 3.087096695846509,
    "VOO": 2.555975696243099,
    "XAUT": 3.1696102443624903,
    "AVGO": 0,
    "FN": 0,
    "MU": 6.701098465481029,
    "SNDK": 5.48491590162198,
    "DRAM": 5.453124582408884,
    "WDC": 1.3131195819898673,
    "ASX": 0,
    "AAOI": 0,
    "GLW": 7.253250955701747,
    "MRVL": 1.4655206257464557,
    "ANET": 0,
    "TSM": 0,
    "ASML": 0,
    "SMH": 3.1821443611734788,
    "SOXX": 0
  },
  "priceErrors": {},
  "priceWarnings": {},
  "positions": [
    {
      "symbol": "USDT",
      "name": "Tether",
      "type": "cash",
      "quantity": 5501.10553647,
      "cost": 1,
      "price": 1,
      "priceOk": true,
      "priceSource": "Fixed 1 USDT",
      "priceUpdatedAt": "2026-07-01T08:55:14.739Z",
      "priceCachedFallback": false,
      "dayHigh": null,
      "dayLow": null,
      "previousClose": null,
      "intradayDropPctFromHigh": 0,
      "dropPctFromPreviousClose": 0,
      "dayLowDropPctFromHigh": 0,
      "reboundPctFromDayLow": 0,
      "priceWarning": null,
      "priceError": null,
      "dataAgeMinutes": 0,
      "isStale": false,
      "isDataBlocked": false,
      "value": 5501.10553647,
      "pnl": 0,
      "pnlPct": 0,
      "weightPct": 34.84586178079543
    },
    {
      "symbol": "USDGO",
      "name": "USDGO",
      "type": "cash",
      "quantity": 1503.71682318,
      "cost": 1.0019,
      "price": 1,
      "priceOk": true,
      "priceSource": "Fixed 1 USDT",
      "priceUpdatedAt": "2026-07-01T08:55:14.739Z",
      "priceCachedFallback": false,
      "dayHigh": null,
      "dayLow": null,
      "previousClose": null,
      "intradayDropPctFromHigh": 0,
      "dropPctFromPreviousClose": 0,
      "dayLowDropPctFromHigh": 0,
      "reboundPctFromDayLow": 0,
      "priceWarning": null,
      "priceError": null,
      "dataAgeMinutes": 0,
      "isStale": false,
      "isDataBlocked": false,
      "value": 1503.71682318,
      "pnl": -2.857061964042032,
      "pnlPct": -0.1896396845992635,
      "weightPct": 9.525050597667775
    },
    {
      "symbol": "BTC",
      "name": "Bitcoin",
      "type": "crypto",
      "quantity": 0.02570715,
      "cost": 59456.98,
      "price": 58804.4,
      "priceOk": true,
      "priceSource": "Bitget BTCUSDT",
      "priceUpdatedAt": "2026-07-01T08:55:14.739Z",
      "priceCachedFallback": false,
      "dayHigh": 59463.98,
      "dayLow": 57802.74,
      "previousClose": 58633,
      "intradayDropPctFromHigh": 1.1092093062052049,
      "dropPctFromPreviousClose": -0.2923268466563223,
      "dayLowDropPctFromHigh": 2.793691239637853,
      "reboundPctFromDayLow": 1.7328936309939695,
      "priceWarning": null,
      "priceError": null,
      "dataAgeMinutes": 0,
      "isStale": false,
      "isDataBlocked": false,
      "value": 1511.69353146,
      "pnl": -16.775971947000244,
      "pnlPct": -1.0975666776213815,
      "weightPct": 9.575577763952422
    },
    {
      "symbol": "ETH",
      "name": "Ethereum",
      "type": "crypto",
      "quantity": 0.2546747,
      "cost": 1570.39,
      "price": 1576.94,
      "priceOk": true,
      "priceSource": "Bitget ETHUSDT",
      "priceUpdatedAt": "2026-07-01T08:55:14.805Z",
      "priceCachedFallback": false,
      "dayHigh": 1604.02,
      "dayLow": 1550.24,
      "previousClose": 1572.19,
      "intradayDropPctFromHigh": 1.6882582511439963,
      "dropPctFromPreviousClose": -0.30212633333121314,
      "dayLowDropPctFromHigh": 3.3528260246131576,
      "reboundPctFromDayLow": 1.7223139642894032,
      "priceWarning": null,
      "priceError": null,
      "dataAgeMinutes": 0,
      "isStale": false,
      "isDataBlocked": false,
      "value": 401.60672141799995,
      "pnl": 1.6681192849999888,
      "pnlPct": 0.4170938429307342,
      "weightPct": 2.543912712089151
    },
    {
      "symbol": "DOGE",
      "name": "Dogecoin",
      "type": "crypto",
      "quantity": 7933.1942142,
      "cost": 0.07309,
      "price": 0.07124,
      "priceOk": true,
      "priceSource": "Bitget DOGEUSDT",
      "priceUpdatedAt": "2026-07-01T08:55:14.807Z",
      "priceCachedFallback": false,
      "dayHigh": 0.07287,
      "dayLow": 0.06952,
      "previousClose": 0.07208,
      "intradayDropPctFromHigh": 2.236860161932217,
      "dropPctFromPreviousClose": 1.165371809101009,
      "dayLowDropPctFromHigh": 4.5972279401674285,
      "reboundPctFromDayLow": 2.4741081703107013,
      "priceWarning": null,
      "priceError": null,
      "dataAgeMinutes": 0,
      "isStale": false,
      "isDataBlocked": false,
      "value": 565.160755819608,
      "pnl": -14.67640929626998,
      "pnlPct": -2.53112600902996,
      "weightPct": 3.579919245442627
    },
    {
      "symbol": "BGB",
      "name": "Bitget Token",
      "type": "crypto",
      "quantity": 25.91259087,
      "cost": 1.978,
      "price": 1.6073,
      "priceOk": true,
      "priceSource": "Bitget BGBUSDT",
      "priceUpdatedAt": "2026-07-01T08:55:14.808Z",
      "priceCachedFallback": false,
      "dayHigh": 1.6282,
      "dayLow": 1.5632,
      "previousClose": 1.5947,
      "intradayDropPctFromHigh": 1.2836260901609224,
      "dropPctFromPreviousClose": -0.7901172634351253,
      "dayLowDropPctFromHigh": 3.992138557916728,
      "reboundPctFromDayLow": 2.821136131013308,
      "priceWarning": null,
      "priceError": null,
      "dataAgeMinutes": 0,
      "isStale": false,
      "isDataBlocked": false,
      "value": 41.649307305350995,
      "pnl": -9.605797435509004,
      "pnlPct": -18.741152679474222,
      "weightPct": 0.2638207894770588
    },
    {
      "symbol": "CRCL",
      "name": "Circle Internet Group",
      "type": "watch",
      "quantity": 7.60903998,
      "cost": 65.7,
      "price": 64.05,
      "priceOk": true,
      "priceSource": "Bitget RCRCLUSDT",
      "priceUpdatedAt": "2026-07-01T08:55:14.808Z",
      "priceCachedFallback": false,
      "dayHigh": 66.18,
      "dayLow": 61.07,
      "previousClose": null,
      "intradayDropPctFromHigh": 3.2184950135992887,
      "dropPctFromPreviousClose": 0,
      "dayLowDropPctFromHigh": 7.721365971592635,
      "reboundPctFromDayLow": 4.8796463075159595,
      "priceWarning": null,
      "priceError": null,
      "dataAgeMinutes": 0,
      "isStale": false,
      "isDataBlocked": false,
      "value": 487.359010719,
      "pnl": -12.554915967,
      "pnlPct": -2.5114155251141552,
      "weightPct": 3.087096695846509
    },
    {
      "symbol": "VOO",
      "name": "Vanguard S&P 500 ETF",
      "type": "watch",
      "quantity": 0.58957511,
      "cost": 677.85,
      "price": 684.41,
      "priceOk": true,
      "priceSource": "Bitget RVOOUSDT",
      "priceUpdatedAt": "2026-07-01T08:55:14.809Z",
      "priceCachedFallback": false,
      "dayHigh": 687.51,
      "dayLow": 682.94,
      "previousClose": null,
      "intradayDropPctFromHigh": 0.45090253232680577,
      "dropPctFromPreviousClose": 0,
      "dayLowDropPctFromHigh": 0.6647176041075673,
      "reboundPctFromDayLow": 0.2152458488300456,
      "priceWarning": null,
      "priceError": null,
      "dataAgeMinutes": 0,
      "isStale": false,
      "isDataBlocked": false,
      "value": 403.51110103509995,
      "pnl": 3.8676127215999827,
      "pnlPct": 0.9677657298812379,
      "weightPct": 2.555975696243099
    },
    {
      "symbol": "XAUT",
      "name": "Tether Gold",
      "type": "watch",
      "quantity": 0.1258369,
      "cost": 3974.69,
      "price": 3976.46,
      "priceOk": true,
      "priceSource": "Bitget XAUTUSDT",
      "priceUpdatedAt": "2026-07-01T08:55:14.810Z",
      "priceCachedFallback": false,
      "dayHigh": 4057.08,
      "dayLow": 3960.37,
      "previousClose": 4001.82,
      "intradayDropPctFromHigh": 1.9871434627860407,
      "dropPctFromPreviousClose": 0.6337116611941598,
      "dayLowDropPctFromHigh": 2.3837341141905024,
      "reboundPctFromDayLow": 0.4062751712592547,
      "priceWarning": null,
      "priceError": null,
      "dataAgeMinutes": 0,
      "isStale": false,
      "isDataBlocked": false,
      "value": 500.38539937400003,
      "pnl": 0.22273131299999704,
      "pnlPct": 0.04453177480507855,
      "weightPct": 3.1696102443624903
    },
    {
      "symbol": "AVGO",
      "name": "Broadcom",
      "type": "watch",
      "quantity": 0,
      "cost": 0,
      "price": 375.9,
      "priceOk": true,
      "priceSource": "Bitget RAVGOUSDT",
      "priceUpdatedAt": "2026-07-01T08:55:14.811Z",
      "priceCachedFallback": false,
      "dayHigh": 379.63,
      "dayLow": 374.02,
      "previousClose": null,
      "intradayDropPctFromHigh": 0.9825356267945152,
      "dropPctFromPreviousClose": 0,
      "dayLowDropPctFromHigh": 1.47775465584912,
      "reboundPctFromDayLow": 0.5026469172771498,
      "priceWarning": null,
      "priceError": null,
      "dataAgeMinutes": 0,
      "isStale": false,
      "isDataBlocked": false,
      "value": 0,
      "pnl": 0,
      "pnlPct": 0,
      "weightPct": 0
    },
    {
      "symbol": "FN",
      "name": "Fabrinet",
      "type": "watch",
      "quantity": 0,
      "cost": 0,
      "price": 550.5,
      "priceOk": true,
      "priceSource": "Bitget RFNUSDT",
      "priceUpdatedAt": "2026-07-01T08:55:14.812Z",
      "priceCachedFallback": false,
      "dayHigh": 586.5,
      "dayLow": 550.5,
      "previousClose": null,
      "intradayDropPctFromHigh": 6.138107416879795,
      "dropPctFromPreviousClose": 0,
      "dayLowDropPctFromHigh": 6.138107416879795,
      "reboundPctFromDayLow": 0,
      "priceWarning": null,
      "priceError": null,
      "dataAgeMinutes": 0,
      "isStale": false,
      "isDataBlocked": false,
      "value": 0,
      "pnl": 0,
      "pnlPct": 0,
      "weightPct": 0
    },
    {
      "symbol": "MU",
      "name": "Micron",
      "type": "watch",
      "quantity": 0.94527129,
      "cost": 1125.24,
      "price": 1119.15,
      "priceOk": true,
      "priceSource": "Bitget RMUUSDT",
      "priceUpdatedAt": "2026-07-01T08:55:14.813Z",
      "priceCachedFallback": false,
      "dayHigh": 1168.51,
      "dayLow": 1104.2,
      "previousClose": null,
      "intradayDropPctFromHigh": 4.224182933821696,
      "dropPctFromPreviousClose": 0,
      "dayLowDropPctFromHigh": 5.50359004201932,
      "reboundPctFromDayLow": 1.3539213910523495,
      "priceWarning": null,
      "priceError": null,
      "dataAgeMinutes": 0,
      "isStale": false,
      "isDataBlocked": false,
      "value": 1057.9003642035,
      "pnl": -5.756702156100118,
      "pnlPct": -0.5412178735203267,
      "weightPct": 6.701098465481029
    },
    {
      "symbol": "SNDK",
      "name": "SanDisk",
      "type": "watch",
      "quantity": 0.39720275,
      "cost": 2075.09,
      "price": 2180,
      "priceOk": true,
      "priceSource": "Bitget RSNDKUSDT",
      "priceUpdatedAt": "2026-07-01T08:55:14.814Z",
      "priceCachedFallback": false,
      "dayHigh": 2280.4,
      "dayLow": 2148.12,
      "previousClose": null,
      "intradayDropPctFromHigh": 4.402736362041751,
      "dropPctFromPreviousClose": 0,
      "dayLowDropPctFromHigh": 5.800736712857402,
      "reboundPctFromDayLow": 1.4840884121929925,
      "priceWarning": null,
      "priceError": null,
      "dataAgeMinutes": 0,
      "isStale": false,
      "isDataBlocked": false,
      "value": 865.9019949999999,
      "pnl": 41.670540502499875,
      "pnlPct": 5.055684331763908,
      "weightPct": 5.48491590162198
    },
    {
      "symbol": "DRAM",
      "name": "Roundhill Memory ETF",
      "type": "watch",
      "quantity": 12.35126412,
      "cost": 71.75,
      "price": 69.7,
      "priceOk": true,
      "priceSource": "Bitget RDRAMUSDT",
      "priceUpdatedAt": "2026-07-01T08:55:14.815Z",
      "priceCachedFallback": false,
      "dayHigh": 74.16,
      "dayLow": 69.04,
      "previousClose": null,
      "intradayDropPctFromHigh": 6.014023732470326,
      "dropPctFromPreviousClose": 0,
      "dayLowDropPctFromHigh": 6.9039913700107745,
      "reboundPctFromDayLow": 0.9559675550405511,
      "priceWarning": null,
      "priceError": null,
      "dataAgeMinutes": 0,
      "isStale": false,
      "isDataBlocked": false,
      "value": 860.883109164,
      "pnl": -25.320091445999992,
      "pnlPct": -2.8571428571428563,
      "weightPct": 5.453124582408884
    },
    {
      "symbol": "WDC",
      "name": "Western Digital",
      "type": "watch",
      "quantity": 0.3305247,
      "cost": 604.3,
      "price": 627.19,
      "priceOk": true,
      "priceSource": "Bitget RWDCUSDT",
      "priceUpdatedAt": "2026-07-01T08:55:14.815Z",
      "priceCachedFallback": false,
      "dayHigh": 648.53,
      "dayLow": 622.5,
      "previousClose": null,
      "intradayDropPctFromHigh": 3.29051855735277,
      "dropPctFromPreviousClose": 0,
      "dayLowDropPctFromHigh": 4.0136925045872935,
      "reboundPctFromDayLow": 0.7534136546184826,
      "priceWarning": null,
      "priceError": null,
      "dataAgeMinutes": 0,
      "isStale": false,
      "isDataBlocked": false,
      "value": 207.30178659300003,
      "pnl": 7.565710383000038,
      "pnlPct": 3.7878537150422167,
      "weightPct": 1.3131195819898673
    },
    {
      "symbol": "ASX",
      "name": "ASE Technology",
      "type": "watch",
      "quantity": 0,
      "cost": 0,
      "price": 44.21,
      "priceOk": true,
      "priceSource": "Bitget RASXUSDT",
      "priceUpdatedAt": "2026-07-01T08:55:14.816Z",
      "priceCachedFallback": false,
      "dayHigh": 45.9,
      "dayLow": 43.98,
      "previousClose": null,
      "intradayDropPctFromHigh": 3.6819172113289715,
      "dropPctFromPreviousClose": 0,
      "dayLowDropPctFromHigh": 4.183006535947716,
      "reboundPctFromDayLow": 0.5229649840836834,
      "priceWarning": null,
      "priceError": null,
      "dataAgeMinutes": 0,
      "isStale": false,
      "isDataBlocked": false,
      "value": 0,
      "pnl": 0,
      "pnlPct": 0,
      "weightPct": 0
    },
    {
      "symbol": "AAOI",
      "name": "Applied Optoelectronics",
      "type": "watch",
      "quantity": 0,
      "cost": 0,
      "price": 145.5,
      "priceOk": true,
      "priceSource": "Bitget RAAOIUSDT",
      "priceUpdatedAt": "2026-07-01T08:55:14.817Z",
      "priceCachedFallback": false,
      "dayHigh": 151.28,
      "dayLow": 144.68,
      "previousClose": null,
      "intradayDropPctFromHigh": 3.8207297726070872,
      "dropPctFromPreviousClose": 0,
      "dayLowDropPctFromHigh": 4.362771020624004,
      "reboundPctFromDayLow": 0.5667680398119941,
      "priceWarning": null,
      "priceError": null,
      "dataAgeMinutes": 0,
      "isStale": false,
      "isDataBlocked": false,
      "value": 0,
      "pnl": 0,
      "pnlPct": 0,
      "weightPct": 0
    },
    {
      "symbol": "GLW",
      "name": "Corning",
      "type": "watch",
      "quantity": 4.65759003,
      "cost": 261.08,
      "price": 245.85,
      "priceOk": true,
      "priceSource": "Bitget RGLWUSDT",
      "priceUpdatedAt": "2026-07-01T08:55:14.818Z",
      "priceCachedFallback": false,
      "dayHigh": 258.7,
      "dayLow": 242.06,
      "previousClose": null,
      "intradayDropPctFromHigh": 4.967143409354462,
      "dropPctFromPreviousClose": 0,
      "dayLowDropPctFromHigh": 6.4321608040200955,
      "reboundPctFromDayLow": 1.5657275055771265,
      "priceWarning": null,
      "priceError": null,
      "dataAgeMinutes": 0,
      "isStale": false,
      "isDataBlocked": false,
      "value": 1145.0685088755,
      "pnl": -70.93509615690004,
      "pnlPct": -5.83346100812012,
      "weightPct": 7.253250955701747
    },
    {
      "symbol": "MRVL",
      "name": "Marvell Technology",
      "type": "watch",
      "quantity": 0.79587648,
      "cost": 251.95,
      "price": 290.7,
      "priceOk": true,
      "priceSource": "Bitget RMRVLUSDT",
      "priceUpdatedAt": "2026-07-01T08:55:14.819Z",
      "priceCachedFallback": false,
      "dayHigh": 299.99,
      "dayLow": 288.64,
      "previousClose": null,
      "intradayDropPctFromHigh": 3.096769892329751,
      "dropPctFromPreviousClose": 0,
      "dayLowDropPctFromHigh": 3.7834594486482955,
      "reboundPctFromDayLow": 0.71369179600887,
      "priceWarning": null,
      "priceError": null,
      "dataAgeMinutes": 0,
      "isStale": false,
      "isDataBlocked": false,
      "value": 231.361292736,
      "pnl": 30.8402136,
      "pnlPct": 15.38003572137329,
      "weightPct": 1.4655206257464557
    },
    {
      "symbol": "ANET",
      "name": "Arista Networks",
      "type": "watch",
      "quantity": 0,
      "cost": 0,
      "price": 168.83,
      "priceOk": true,
      "priceSource": "Bitget RANETUSDT",
      "priceUpdatedAt": "2026-07-01T08:55:14.820Z",
      "priceCachedFallback": false,
      "dayHigh": 172.54,
      "dayLow": 168.61,
      "previousClose": null,
      "intradayDropPctFromHigh": 2.150226034542703,
      "dropPctFromPreviousClose": 0,
      "dayLowDropPctFromHigh": 2.2777326996638334,
      "reboundPctFromDayLow": 0.13047861929897328,
      "priceWarning": null,
      "priceError": null,
      "dataAgeMinutes": 0,
      "isStale": false,
      "isDataBlocked": false,
      "value": 0,
      "pnl": 0,
      "pnlPct": 0,
      "weightPct": 0
    },
    {
      "symbol": "TSM",
      "name": "Taiwan Semiconductor Manufacturing",
      "type": "watch",
      "quantity": 0,
      "cost": 0,
      "price": 473.9,
      "priceOk": true,
      "priceSource": "Bitget RTSMUSDT",
      "priceUpdatedAt": "2026-07-01T08:55:14.821Z",
      "priceCachedFallback": false,
      "dayHigh": 478.55,
      "dayLow": 467.81,
      "previousClose": null,
      "intradayDropPctFromHigh": 0.9716852993417686,
      "dropPctFromPreviousClose": 0,
      "dayLowDropPctFromHigh": 2.2442795946087157,
      "reboundPctFromDayLow": 1.3018105641179059,
      "priceWarning": null,
      "priceError": null,
      "dataAgeMinutes": 0,
      "isStale": false,
      "isDataBlocked": false,
      "value": 0,
      "pnl": 0,
      "pnlPct": 0,
      "weightPct": 0
    },
    {
      "symbol": "ASML",
      "name": "ASML Holding",
      "type": "watch",
      "quantity": 0,
      "cost": 0,
      "price": 1971.66,
      "priceOk": true,
      "priceSource": "Bitget RASMLUSDT",
      "priceUpdatedAt": "2026-07-01T08:55:14.822Z",
      "priceCachedFallback": false,
      "dayHigh": 1999.94,
      "dayLow": 1937.63,
      "previousClose": null,
      "intradayDropPctFromHigh": 1.4140424212726368,
      "dropPctFromPreviousClose": 0,
      "dayLowDropPctFromHigh": 3.1155934678040316,
      "reboundPctFromDayLow": 1.7562692567724474,
      "priceWarning": null,
      "priceError": null,
      "dataAgeMinutes": 0,
      "isStale": false,
      "isDataBlocked": false,
      "value": 0,
      "pnl": 0,
      "pnlPct": 0,
      "weightPct": 0
    },
    {
      "symbol": "SMH",
      "name": "VanEck Semiconductor ETF",
      "type": "watch",
      "quantity": 0.77387993,
      "cost": 650.85,
      "price": 649.15,
      "priceOk": true,
      "priceSource": "Bitget RSMHUSDT",
      "priceUpdatedAt": "2026-07-01T08:55:14.823Z",
      "priceCachedFallback": false,
      "dayHigh": 659.62,
      "dayLow": 646.29,
      "previousClose": null,
      "intradayDropPctFromHigh": 1.5872775234225807,
      "dropPctFromPreviousClose": 0,
      "dayLowDropPctFromHigh": 2.020860495436773,
      "reboundPctFromDayLow": 0.4425258011109585,
      "priceWarning": null,
      "priceError": null,
      "dataAgeMinutes": 0,
      "isStale": false,
      "isDataBlocked": false,
      "value": 502.3641565595,
      "pnl": -1.3155958810000357,
      "pnlPct": -0.26119689636629734,
      "weightPct": 3.1821443611734788
    },
    {
      "symbol": "SOXX",
      "name": "iShares Semiconductor ETF",
      "type": "watch",
      "quantity": 0,
      "cost": 0,
      "price": 632.1,
      "priceOk": true,
      "priceSource": "Bitget RSOXXUSDT",
      "priceUpdatedAt": "2026-07-01T08:55:14.824Z",
      "priceCachedFallback": false,
      "dayHigh": 644.9,
      "dayLow": 629.5,
      "previousClose": null,
      "intradayDropPctFromHigh": 1.9848038455574437,
      "dropPctFromPreviousClose": 0,
      "dayLowDropPctFromHigh": 2.3879671266863043,
      "reboundPctFromDayLow": 0.4130262112787963,
      "priceWarning": null,
      "priceError": null,
      "dataAgeMinutes": 0,
      "isStale": false,
      "isDataBlocked": false,
      "value": 0,
      "pnl": 0,
      "pnlPct": 0,
      "weightPct": 0
    }
  ],
  "bitgetSync": {
    "enabled": false,
    "used": false,
    "source": "disabled-holdings-json-mode"
  },
  "holdingsSource": {
    "mode": "holdings-json-only",
    "file": "config/holdings.json",
    "note": "页面和邮件均以 holdings.json 为唯一仓位来源。"
  },
  "btcFiveMinuteChangePct": -0.006138619551997394,
  "highWatermark": 15898.080640078653,
  "drawdownPct": 0.6988971982315095,
  "btcWeeklyGainPct": -0.33152542372881105,
  "buyPauseUntil": null,
  "buyPaused": false,
  "healthSummary": {
    "score": {
      "total": 99,
      "grade": "优秀",
      "components": [
        {
          "label": "现金安全",
          "max": 20,
          "score": 20,
          "reasons": []
        },
        {
          "label": "核心仓完整度",
          "max": 25,
          "score": 24,
          "reasons": [
            "BTC/ETH 合计达标，但 ETH 偏低，仅作为结构提示。"
          ]
        },
        {
          "label": "投机仓控制",
          "max": 15,
          "score": 15,
          "reasons": []
        },
        {
          "label": "AI抽水机仓控制",
          "max": 15,
          "score": 15,
          "reasons": []
        },
        {
          "label": "数据与纪律",
          "max": 15,
          "score": 15,
          "reasons": []
        },
        {
          "label": "回撤状态",
          "max": 10,
          "score": 10,
          "reasons": []
        }
      ],
      "reasons": [
        "核心仓完整度：BTC/ETH 合计达标，但 ETH 偏低，仅作为结构提示。"
      ],
      "topAdvice": [
        "BTC/ETH 总量达标但 ETH 偏低，这是结构偏科，不是核心不足。"
      ],
      "layers": [
        {
          "id": "cash",
          "name": "安全现金层",
          "symbols": [
            "USDT",
            "USDGO"
          ],
          "value": 7004.822359649999,
          "weightPct": 44.37091237846321,
          "targetText": "成熟目标 35%-45%，阶段目标 65% / 50%",
          "status": {
            "label": "健康",
            "level": ""
          },
          "advice": "现金处于可执行区间，继续按 AI 优先规则分批。"
        },
        {
          "id": "core",
          "name": "核心增长层",
          "symbols": [
            "BTC",
            "ETH"
          ],
          "value": 1913.300252878,
          "weightPct": 12.119490476041573,
          "targetText": "BTC 5%-8%，ETH 3%-5%；当前阶段只做底仓，不抢 AI 主攻资金",
          "status": {
            "label": "核心偏科",
            "level": "info"
          },
          "advice": "BTC/ETH 合计已达标，但 ETH 低于单项底仓线；这只是结构提示，不影响 AI 主攻仓优先级。"
        },
        {
          "id": "stable",
          "name": "长期稳定层",
          "symbols": [
            "VOO",
            "XAUT"
          ],
          "value": 903.8965004091,
          "weightPct": 5.725585940605589,
          "targetText": "VOO 5%-7%，XAUT 3%-4%；保险底仓，不做当前主攻",
          "status": {
            "label": "健康",
            "level": ""
          },
          "advice": "稳定层已建立，当前不继续抢 AI 主攻资金。"
        },
        {
          "id": "theme",
          "name": "AI抽水机主攻仓",
          "symbols": [
            "MU",
            "DRAM",
            "GLW",
            "SMH",
            "MRVL",
            "ANET",
            "AVGO",
            "TSM",
            "ASML",
            "SOXX",
            "WDC",
            "SNDK",
            "FN",
            "AAOI",
            "ASX"
          ],
          "value": 4870.7812131314995,
          "weightPct": 30.853174474123442,
          "targetText": "目标 25%-35%，35% 停止新增，40% 硬上限；MU/DRAM/GLW/SMH 单笔 500 USDT 起",
          "status": {
            "label": "健康",
            "level": ""
          },
          "advice": "AI 抽水机仓是收益主攻层，35% 后停止新增，40% 为硬上限。"
        },
        {
          "id": "speculative",
          "name": "投机清理层",
          "symbols": [
            "DOGE",
            "BGB"
          ],
          "value": 606.810063124959,
          "weightPct": 3.8437400349196857,
          "targetText": "DOGE 可作为 BTC 高弹性卫星；DOGE+BGB 目标 0%-4%，4.5% 禁止新增，5% 只减不补",
          "status": {
            "label": "健康",
            "level": ""
          },
          "advice": "DOGE 可适度作为 BTC 放大器，但仍不能摊低成本或替代核心仓。"
        },
        {
          "id": "cryptoFinance",
          "name": "加密金融基础设施卫星仓",
          "symbols": [
            "CRCL"
          ],
          "value": 487.359010719,
          "weightPct": 3.087096695846509,
          "targetText": "CRCL 目标上限 4%，4.5% 禁止新增，5% 硬上限；不与 DOGE/BGB 合并计算投机仓上限",
          "status": {
            "label": "小仓观察",
            "level": "info"
          },
          "advice": "CRCL 只做加密金融基础设施小仓观察，不抢 AI 主攻资金，也不纳入 DOGE/BGB 投机仓合计。"
        }
      ]
    },
    "layers": [
      {
        "id": "cash",
        "name": "安全现金层",
        "symbols": [
          "USDT",
          "USDGO"
        ],
        "value": 7004.822359649999,
        "weightPct": 44.37091237846321,
        "targetText": "成熟目标 35%-45%，阶段目标 65% / 50%",
        "status": {
          "label": "健康",
          "level": ""
        },
        "advice": "现金处于可执行区间，继续按 AI 优先规则分批。"
      },
      {
        "id": "core",
        "name": "核心增长层",
        "symbols": [
          "BTC",
          "ETH"
        ],
        "value": 1913.300252878,
        "weightPct": 12.119490476041573,
        "targetText": "BTC 5%-8%，ETH 3%-5%；当前阶段只做底仓，不抢 AI 主攻资金",
        "status": {
          "label": "核心偏科",
          "level": "info"
        },
        "advice": "BTC/ETH 合计已达标，但 ETH 低于单项底仓线；这只是结构提示，不影响 AI 主攻仓优先级。"
      },
      {
        "id": "stable",
        "name": "长期稳定层",
        "symbols": [
          "VOO",
          "XAUT"
        ],
        "value": 903.8965004091,
        "weightPct": 5.725585940605589,
        "targetText": "VOO 5%-7%，XAUT 3%-4%；保险底仓，不做当前主攻",
        "status": {
          "label": "健康",
          "level": ""
        },
        "advice": "稳定层已建立，当前不继续抢 AI 主攻资金。"
      },
      {
        "id": "theme",
        "name": "AI抽水机主攻仓",
        "symbols": [
          "MU",
          "DRAM",
          "GLW",
          "SMH",
          "MRVL",
          "ANET",
          "AVGO",
          "TSM",
          "ASML",
          "SOXX",
          "WDC",
          "SNDK",
          "FN",
          "AAOI",
          "ASX"
        ],
        "value": 4870.7812131314995,
        "weightPct": 30.853174474123442,
        "targetText": "目标 25%-35%，35% 停止新增，40% 硬上限；MU/DRAM/GLW/SMH 单笔 500 USDT 起",
        "status": {
          "label": "健康",
          "level": ""
        },
        "advice": "AI 抽水机仓是收益主攻层，35% 后停止新增，40% 为硬上限。"
      },
      {
        "id": "speculative",
        "name": "投机清理层",
        "symbols": [
          "DOGE",
          "BGB"
        ],
        "value": 606.810063124959,
        "weightPct": 3.8437400349196857,
        "targetText": "DOGE 可作为 BTC 高弹性卫星；DOGE+BGB 目标 0%-4%，4.5% 禁止新增，5% 只减不补",
        "status": {
          "label": "健康",
          "level": ""
        },
        "advice": "DOGE 可适度作为 BTC 放大器，但仍不能摊低成本或替代核心仓。"
      },
      {
        "id": "cryptoFinance",
        "name": "加密金融基础设施卫星仓",
        "symbols": [
          "CRCL"
        ],
        "value": 487.359010719,
        "weightPct": 3.087096695846509,
        "targetText": "CRCL 目标上限 4%，4.5% 禁止新增，5% 硬上限；不与 DOGE/BGB 合并计算投机仓上限",
        "status": {
          "label": "小仓观察",
          "level": "info"
        },
        "advice": "CRCL 只做加密金融基础设施小仓观察，不抢 AI 主攻资金，也不纳入 DOGE/BGB 投机仓合计。"
      }
    ],
    "judgement": [
      "BTC/ETH 合计已达标，但 ETH 偏低，这是核心偏科，不是核心不足；不影响 AI 主攻仓优先。"
    ],
    "allowedActions": [
      "AI 主攻仓进入健康进攻区，后续只在急跌或深回调时继续加，不追涨。",
      "CRCL 独立归属加密金融基础设施卫星仓，55-60 区间才允许 100-200 USDT 小补；不抢 AI 主攻资金，也不与 DOGE/BGB 合并计算投机仓上限。 允许做月度复盘、更新持仓成本和检查价格源。"
    ],
    "forbiddenActions": [
      "不要因为刚买就跌而立刻补同一个标的。"
    ],
    "phasePlan": [
      {
        "name": "第一阶段：现金降到 60%-65%",
        "deployAmount": 0,
        "target": "新增资金优先 AI 主攻仓；BTC/XAUT 弱势阶段只保留底仓，不继续机械补仓。",
        "steps": [
          "MU/DRAM/GLW/SMH 建立有效主攻仓，单笔 500 USDT 起",
          "AI A/S 急跌机会执行 1000-2500 USDT",
          "BTC 只在 56k/55k 或趋势确认后小额补",
          "XAUT 3850 以下才补，3900 上方不补"
        ]
      },
      {
        "name": "第二阶段：现金降到 45%-50%",
        "deployAmount": 0,
        "target": "AI 主攻仓推进到 25%-35%，让账户真正吃到主升方向。",
        "steps": [
          "AI 抽水机仓推进到 25% 以上",
          "MU/DRAM/GLW/SMH 单项向 4%-8% 目标靠拢",
          "MRVL/ANET/AVGO 只做第二梯队",
          "不因 BTC/XAUT 目标不足而挤占 AI 弹药"
        ]
      },
      {
        "name": "第三阶段：现金稳定 35%-45%",
        "deployAmount": 0,
        "target": "形成趋势优先结构：现金有防守，AI 主攻仓能真正影响账户收益。",
        "steps": [
          "现金保留 35%-45%",
          "AI 抽水机仓 25%-35%",
          "AI 35% 后停止新增，40% 硬上限",
          "BTC/XAUT 只做保险底仓",
          "每月复盘再平衡"
        ]
      }
    ],
    "freshness": {
      "ageMinutes": 0,
      "isStale": false,
      "isBlocked": false,
      "missingPrices": [],
      "label": "数据新鲜"
    },
    "cooldown": {
      "configured": false,
      "status": "未配置交易记录",
      "blockedSymbols": [],
      "messages": [
        "冷却机制：未配置交易记录；页面只显示规则，不伪造最近交易。"
      ]
    },
    "rebalanceAlerts": []
  }
}
