{
  "updatedAt": "2026-06-30T18:45:13.991Z",
  "source": "github-actions",
  "totalValue": 15987.93293621887,
  "cashValue": 8004.286823179999,
  "cashPct": 50.06455090293246,
  "dataAgeMinutes": 0,
  "isStale": false,
  "isDataBlocked": false,
  "weights": {
    "USDT": 40.65922734310254,
    "USDGO": 9.405323559829915,
    "BTC": 9.40385737591211,
    "ETH": 2.509101095509551,
    "DOGE": 3.5790824301867246,
    "BGB": 0.258170747660046,
    "VOO": 2.531997498633104,
    "XAUT": 3.168249250454985,
    "AVGO": 0,
    "FN": 0,
    "MU": 6.833852912100699,
    "SNDK": 5.620338143772027,
    "DRAM": 5.6920500229270035,
    "WDC": 1.3313246756484027,
    "ASX": 0,
    "AAOI": 0,
    "GLW": 4.345931305075423,
    "MRVL": 1.4814475479280782,
    "ANET": 0,
    "TSM": 0,
    "ASML": 0,
    "SMH": 3.180046091259385,
    "SOXX": 0
  },
  "priceErrors": {},
  "priceWarnings": {},
  "positions": [
    {
      "symbol": "USDT",
      "name": "Tether",
      "type": "cash",
      "quantity": 6500.57,
      "cost": 1,
      "price": 1,
      "priceOk": true,
      "priceSource": "Fixed 1 USDT",
      "priceUpdatedAt": "2026-06-30T18:45:13.382Z",
      "priceCachedFallback": false,
      "dayHigh": null,
      "dayLow": null,
      "previousClose": null,
      "intradayDropPctFromHigh": 0,
      "dropPctFromPreviousClose": 0,
      "dayLowDropPctFromHigh": 0,
      "reboundPctFromDayLow": 0,
      "priceWarning": null,
      "priceError": null,
      "dataAgeMinutes": 0,
      "isStale": false,
      "isDataBlocked": false,
      "value": 6500.57,
      "pnl": 0,
      "pnlPct": 0,
      "weightPct": 40.65922734310254
    },
    {
      "symbol": "USDGO",
      "name": "USDGO",
      "type": "cash",
      "quantity": 1503.71682318,
      "cost": 1.0019,
      "price": 1,
      "priceOk": true,
      "priceSource": "Fixed 1 USDT",
      "priceUpdatedAt": "2026-06-30T18:45:13.382Z",
      "priceCachedFallback": false,
      "dayHigh": null,
      "dayLow": null,
      "previousClose": null,
      "intradayDropPctFromHigh": 0,
      "dropPctFromPreviousClose": 0,
      "dayLowDropPctFromHigh": 0,
      "reboundPctFromDayLow": 0,
      "priceWarning": null,
      "priceError": null,
      "dataAgeMinutes": 0,
      "isStale": false,
      "isDataBlocked": false,
      "value": 1503.71682318,
      "pnl": -2.857061964042032,
      "pnlPct": -0.1896396845992635,
      "weightPct": 9.405323559829915
    },
    {
      "symbol": "BTC",
      "name": "Bitcoin",
      "type": "crypto",
      "quantity": 0.02570715,
      "cost": 59456.98,
      "price": 58484.99,
      "priceOk": true,
      "priceSource": "Bitget BTCUSDT",
      "priceUpdatedAt": "2026-06-30T18:45:13.382Z",
      "priceCachedFallback": false,
      "dayHigh": 60588.83,
      "dayLow": 58196,
      "previousClose": 60258.1,
      "intradayDropPctFromHigh": 3.472323198847054,
      "dropPctFromPreviousClose": 2.942525569176593,
      "dayLowDropPctFromHigh": 3.949292303548363,
      "reboundPctFromDayLow": 0.49658052099800326,
      "priceWarning": null,
      "priceError": null,
      "dataAgeMinutes": 0,
      "isStale": false,
      "isDataBlocked": false,
      "value": 1503.4824106785,
      "pnl": -24.98709272850033,
      "pnlPct": -1.6347786248141305,
      "weightPct": 9.40385737591211
    },
    {
      "symbol": "ETH",
      "name": "Ethereum",
      "type": "crypto",
      "quantity": 0.2546747,
      "cost": 1570.39,
      "price": 1575.16,
      "priceOk": true,
      "priceSource": "Bitget ETHUSDT",
      "priceUpdatedAt": "2026-06-30T18:45:13.439Z",
      "priceCachedFallback": false,
      "dayHigh": 1627.49,
      "dayLow": 1550.24,
      "previousClose": 1613.02,
      "intradayDropPctFromHigh": 3.2153807396665983,
      "dropPctFromPreviousClose": 2.347150066335191,
      "dayLowDropPctFromHigh": 4.7465729436125565,
      "reboundPctFromDayLow": 1.6074930333367783,
      "priceWarning": null,
      "priceError": null,
      "dataAgeMinutes": 0,
      "isStale": false,
      "isDataBlocked": false,
      "value": 401.15340045199997,
      "pnl": 1.2147983190000105,
      "pnlPct": 0.303746203172463,
      "weightPct": 2.509101095509551
    },
    {
      "symbol": "DOGE",
      "name": "Dogecoin",
      "type": "crypto",
      "quantity": 7933.1942142,
      "cost": 0.07309,
      "price": 0.07213,
      "priceOk": true,
      "priceSource": "Bitget DOGEUSDT",
      "priceUpdatedAt": "2026-06-30T18:45:13.440Z",
      "priceCachedFallback": false,
      "dayHigh": 0.07413,
      "dayLow": 0.06952,
      "previousClose": 0.07347,
      "intradayDropPctFromHigh": 2.697963037906383,
      "dropPctFromPreviousClose": 1.8238736899414645,
      "dayLowDropPctFromHigh": 6.218804802374212,
      "reboundPctFromDayLow": 3.7543153049482183,
      "priceWarning": null,
      "priceError": null,
      "dataAgeMinutes": 0,
      "isStale": false,
      "isDataBlocked": false,
      "value": 572.221298670246,
      "pnl": -7.615866445631923,
      "pnlPct": -1.313449172253373,
      "weightPct": 3.5790824301867246
    },
    {
      "symbol": "BGB",
      "name": "Bitget Token",
      "type": "crypto",
      "quantity": 25.91259087,
      "cost": 1.978,
      "price": 1.5929,
      "priceOk": true,
      "priceSource": "Bitget BGBUSDT",
      "priceUpdatedAt": "2026-06-30T18:45:13.441Z",
      "priceCachedFallback": false,
      "dayHigh": 1.6358,
      "dayLow": 1.588,
      "previousClose": 1.624,
      "intradayDropPctFromHigh": 2.6225699963320666,
      "dropPctFromPreviousClose": 1.9150246305418797,
      "dayLowDropPctFromHigh": 2.922117618290735,
      "reboundPctFromDayLow": 0.3085642317380292,
      "priceWarning": null,
      "priceError": null,
      "dataAgeMinutes": 0,
      "isStale": false,
      "isDataBlocked": false,
      "value": 41.276165996822996,
      "pnl": -9.978938744037002,
      "pnlPct": -19.469160768452987,
      "weightPct": 0.258170747660046
    },
    {
      "symbol": "VOO",
      "name": "Vanguard S&P 500 ETF",
      "type": "watch",
      "quantity": 0.58957511,
      "cost": 677.85,
      "price": 686.62,
      "priceOk": true,
      "priceSource": "Bitget RVOOUSDT",
      "priceUpdatedAt": "2026-06-30T18:45:13.442Z",
      "priceCachedFallback": false,
      "dayHigh": 686.73,
      "dayLow": 685.49,
      "previousClose": null,
      "intradayDropPctFromHigh": 0.01601794009290604,
      "dropPctFromPreviousClose": 0,
      "dayLowDropPctFromHigh": 0.18056587013819247,
      "reboundPctFromDayLow": 0.16484558491006365,
      "priceWarning": null,
      "priceError": null,
      "dataAgeMinutes": 0,
      "isStale": false,
      "isDataBlocked": false,
      "value": 404.8140620282,
      "pnl": 5.170573714700026,
      "pnlPct": 1.2937965626613626,
      "weightPct": 2.531997498633104
    },
    {
      "symbol": "XAUT",
      "name": "Tether Gold",
      "type": "watch",
      "quantity": 0.1258369,
      "cost": 3974.69,
      "price": 4025.35,
      "priceOk": true,
      "priceSource": "Bitget XAUTUSDT",
      "priceUpdatedAt": "2026-06-30T18:45:13.443Z",
      "priceCachedFallback": false,
      "dayHigh": 4057.08,
      "dayLow": 3943.88,
      "previousClose": 4011.52,
      "intradayDropPctFromHigh": 0.7820895816695755,
      "dropPctFromPreviousClose": -0.3447570995532847,
      "dayLowDropPctFromHigh": 2.79018407327437,
      "reboundPctFromDayLow": 2.0657322230899466,
      "priceWarning": null,
      "priceError": null,
      "dataAgeMinutes": 0,
      "isStale": false,
      "isDataBlocked": false,
      "value": 506.537565415,
      "pnl": 6.374897353999984,
      "pnlPct": 1.274564808827855,
      "weightPct": 3.168249250454985
    },
    {
      "symbol": "AVGO",
      "name": "Broadcom",
      "type": "watch",
      "quantity": 0,
      "cost": 0,
      "price": 378.22,
      "priceOk": true,
      "priceSource": "Bitget RAVGOUSDT",
      "priceUpdatedAt": "2026-06-30T18:45:13.443Z",
      "priceCachedFallback": false,
      "dayHigh": 378.32,
      "dayLow": 374.02,
      "previousClose": null,
      "intradayDropPctFromHigh": 0.02643264960878777,
      "dropPctFromPreviousClose": 0,
      "dayLowDropPctFromHigh": 1.1366039331782647,
      "reboundPctFromDayLow": 1.1229346024276898,
      "priceWarning": null,
      "priceError": null,
      "dataAgeMinutes": 0,
      "isStale": false,
      "isDataBlocked": false,
      "value": 0,
      "pnl": 0,
      "pnlPct": 0,
      "weightPct": 0
    },
    {
      "symbol": "FN",
      "name": "Fabrinet",
      "type": "watch",
      "quantity": 0,
      "cost": 0,
      "price": 572.58,
      "priceOk": true,
      "priceSource": "Bitget RFNUSDT",
      "priceUpdatedAt": "2026-06-30T18:45:13.444Z",
      "priceCachedFallback": false,
      "dayHigh": 572.99,
      "dayLow": 556.97,
      "previousClose": null,
      "intradayDropPctFromHigh": 0.07155447739052481,
      "dropPctFromPreviousClose": 0,
      "dayLowDropPctFromHigh": 2.795860311698281,
      "reboundPctFromDayLow": 2.8026644163958587,
      "priceWarning": null,
      "priceError": null,
      "dataAgeMinutes": 0,
      "isStale": false,
      "isDataBlocked": false,
      "value": 0,
      "pnl": 0,
      "pnlPct": 0,
      "weightPct": 0
    },
    {
      "symbol": "MU",
      "name": "Micron",
      "type": "watch",
      "quantity": 0.94527129,
      "cost": 1125.24,
      "price": 1155.85,
      "priceOk": true,
      "priceSource": "Bitget RMUUSDT",
      "priceUpdatedAt": "2026-06-30T18:45:13.445Z",
      "priceCachedFallback": false,
      "dayHigh": 1166.05,
      "dayLow": 1143.85,
      "previousClose": null,
      "intradayDropPctFromHigh": 0.8747480811286006,
      "dropPctFromPreviousClose": 0,
      "dayLowDropPctFromHigh": 1.9038634706916553,
      "reboundPctFromDayLow": 1.0490886042750363,
      "priceWarning": null,
      "priceError": null,
      "dataAgeMinutes": 0,
      "isStale": false,
      "isDataBlocked": false,
      "value": 1092.5918205465,
      "pnl": 28.93475418689991,
      "pnlPct": 2.7203085563968488,
      "weightPct": 6.833852912100699
    },
    {
      "symbol": "SNDK",
      "name": "SanDisk",
      "type": "watch",
      "quantity": 0.39720275,
      "cost": 2075.05,
      "price": 2262.26,
      "priceOk": true,
      "priceSource": "Bitget RSNDKUSDT",
      "priceUpdatedAt": "2026-06-30T18:45:13.446Z",
      "priceCachedFallback": false,
      "dayHigh": 2263.01,
      "dayLow": 2184.19,
      "previousClose": null,
      "intradayDropPctFromHigh": 0.03314170065532189,
      "dropPctFromPreviousClose": 0,
      "dayLowDropPctFromHigh": 3.4829717942033023,
      "reboundPctFromDayLow": 3.574322746647506,
      "priceWarning": null,
      "priceError": null,
      "dataAgeMinutes": 0,
      "isStale": false,
      "isDataBlocked": false,
      "value": 898.5758932150001,
      "pnl": 74.36032682749999,
      "pnlPct": 9.02195127828245,
      "weightPct": 5.620338143772027
    },
    {
      "symbol": "DRAM",
      "name": "Roundhill Memory ETF",
      "type": "watch",
      "quantity": 12.35126412,
      "cost": 69.52,
      "price": 73.68,
      "priceOk": true,
      "priceSource": "Bitget RDRAMUSDT",
      "priceUpdatedAt": "2026-06-30T18:45:13.447Z",
      "priceCachedFallback": false,
      "dayHigh": 73.91,
      "dayLow": 73.07,
      "previousClose": null,
      "intradayDropPctFromHigh": 0.3111892842646324,
      "dropPctFromPreviousClose": 0,
      "dayLowDropPctFromHigh": 1.1365173860100168,
      "reboundPctFromDayLow": 0.8348159299302226,
      "priceWarning": null,
      "priceError": null,
      "dataAgeMinutes": 0,
      "isStale": false,
      "isDataBlocked": false,
      "value": 910.0411403616,
      "pnl": 51.38125873920012,
      "pnlPct": 5.98388952819334,
      "weightPct": 5.6920500229270035
    },
    {
      "symbol": "WDC",
      "name": "Western Digital",
      "type": "watch",
      "quantity": 0.3305247,
      "cost": 604.3,
      "price": 643.98,
      "priceOk": true,
      "priceSource": "Bitget RWDCUSDT",
      "priceUpdatedAt": "2026-06-30T18:45:13.447Z",
      "priceCachedFallback": false,
      "dayHigh": 644.42,
      "dayLow": 633.82,
      "previousClose": null,
      "intradayDropPctFromHigh": 0.06827845194127137,
      "dropPctFromPreviousClose": 0,
      "dayLowDropPctFromHigh": 1.6448899785853806,
      "reboundPctFromDayLow": 1.602978763686846,
      "priceWarning": null,
      "priceError": null,
      "dataAgeMinutes": 0,
      "isStale": false,
      "isDataBlocked": false,
      "value": 212.85129630600002,
      "pnl": 13.11522009600003,
      "pnlPct": 6.566275028959141,
      "weightPct": 1.3313246756484027
    },
    {
      "symbol": "ASX",
      "name": "ASE Technology",
      "type": "watch",
      "quantity": 0,
      "cost": 0,
      "price": 45.09,
      "priceOk": true,
      "priceSource": "Bitget RASXUSDT",
      "priceUpdatedAt": "2026-06-30T18:45:13.448Z",
      "priceCachedFallback": false,
      "dayHigh": 45.09,
      "dayLow": 44.62,
      "previousClose": null,
      "intradayDropPctFromHigh": 0,
      "dropPctFromPreviousClose": 0,
      "dayLowDropPctFromHigh": 1.0423597249944687,
      "reboundPctFromDayLow": 1.0533393097265935,
      "priceWarning": null,
      "priceError": null,
      "dataAgeMinutes": 0,
      "isStale": false,
      "isDataBlocked": false,
      "value": 0,
      "pnl": 0,
      "pnlPct": 0,
      "weightPct": 0
    },
    {
      "symbol": "AAOI",
      "name": "Applied Optoelectronics",
      "type": "watch",
      "quantity": 0,
      "cost": 0,
      "price": 150.22,
      "priceOk": true,
      "priceSource": "Bitget RAAOIUSDT",
      "priceUpdatedAt": "2026-06-30T18:45:13.449Z",
      "priceCachedFallback": false,
      "dayHigh": 151.28,
      "dayLow": 144.91,
      "previousClose": null,
      "intradayDropPctFromHigh": 0.700687466948706,
      "dropPctFromPreviousClose": 0,
      "dayLowDropPctFromHigh": 4.210735060814387,
      "reboundPctFromDayLow": 3.664343385549653,
      "priceWarning": null,
      "priceError": null,
      "dataAgeMinutes": 0,
      "isStale": false,
      "isDataBlocked": false,
      "value": 0,
      "pnl": 0,
      "pnlPct": 0,
      "weightPct": 0
    },
    {
      "symbol": "GLW",
      "name": "Corning",
      "type": "watch",
      "quantity": 2.74265644,
      "cost": 261.12,
      "price": 253.34,
      "priceOk": true,
      "priceSource": "Bitget RGLWUSDT",
      "priceUpdatedAt": "2026-06-30T18:45:13.450Z",
      "priceCachedFallback": false,
      "dayHigh": 258.7,
      "dayLow": 250.69,
      "previousClose": null,
      "intradayDropPctFromHigh": 2.0718979512949307,
      "dropPctFromPreviousClose": 0,
      "dayLowDropPctFromHigh": 3.096250483185153,
      "reboundPctFromDayLow": 1.0570824524312918,
      "priceWarning": null,
      "priceError": null,
      "dataAgeMinutes": 0,
      "isStale": false,
      "isDataBlocked": false,
      "value": 694.8245825096001,
      "pnl": -21.337867103199983,
      "pnlPct": -2.9794730392156836,
      "weightPct": 4.345931305075423
    },
    {
      "symbol": "MRVL",
      "name": "Marvell Technology",
      "type": "watch",
      "quantity": 0.79587648,
      "cost": 251.95,
      "price": 297.6,
      "priceOk": true,
      "priceSource": "Bitget RMRVLUSDT",
      "priceUpdatedAt": "2026-06-30T18:45:13.451Z",
      "priceCachedFallback": false,
      "dayHigh": 298.12,
      "dayLow": 290.17,
      "previousClose": null,
      "intradayDropPctFromHigh": 0.17442640547429955,
      "dropPctFromPreviousClose": 0,
      "dayLowDropPctFromHigh": 2.6667113913860154,
      "reboundPctFromDayLow": 2.5605679429300086,
      "priceWarning": null,
      "priceError": null,
      "dataAgeMinutes": 0,
      "isStale": false,
      "isDataBlocked": false,
      "value": 236.85284044800002,
      "pnl": 36.331761312000026,
      "pnlPct": 18.118674340146868,
      "weightPct": 1.4814475479280782
    },
    {
      "symbol": "ANET",
      "name": "Arista Networks",
      "type": "watch",
      "quantity": 0,
      "cost": 0,
      "price": 171.77,
      "priceOk": true,
      "priceSource": "Bitget RANETUSDT",
      "priceUpdatedAt": "2026-06-30T18:45:13.451Z",
      "priceCachedFallback": false,
      "dayHigh": 171.93,
      "dayLow": 169.12,
      "previousClose": null,
      "intradayDropPctFromHigh": 0.09306112952945768,
      "dropPctFromPreviousClose": 0,
      "dayLowDropPctFromHigh": 1.6343860873611367,
      "reboundPctFromDayLow": 1.5669347209082343,
      "priceWarning": null,
      "priceError": null,
      "dataAgeMinutes": 0,
      "isStale": false,
      "isDataBlocked": false,
      "value": 0,
      "pnl": 0,
      "pnlPct": 0,
      "weightPct": 0
    },
    {
      "symbol": "TSM",
      "name": "Taiwan Semiconductor Manufacturing",
      "type": "watch",
      "quantity": 0,
      "cost": 0,
      "price": 474.33,
      "priceOk": true,
      "priceSource": "Bitget RTSMUSDT",
      "priceUpdatedAt": "2026-06-30T18:45:13.452Z",
      "priceCachedFallback": false,
      "dayHigh": 474.69,
      "dayLow": 467.81,
      "previousClose": null,
      "intradayDropPctFromHigh": 0.07583896859003005,
      "dropPctFromPreviousClose": 0,
      "dayLowDropPctFromHigh": 1.449366955276074,
      "reboundPctFromDayLow": 1.3937282229965118,
      "priceWarning": null,
      "priceError": null,
      "dataAgeMinutes": 0,
      "isStale": false,
      "isDataBlocked": false,
      "value": 0,
      "pnl": 0,
      "pnlPct": 0,
      "weightPct": 0
    },
    {
      "symbol": "ASML",
      "name": "ASML Holding",
      "type": "watch",
      "quantity": 0,
      "cost": 0,
      "price": 1983.24,
      "priceOk": true,
      "priceSource": "Bitget RASMLUSDT",
      "priceUpdatedAt": "2026-06-30T18:45:13.453Z",
      "priceCachedFallback": false,
      "dayHigh": 1985.61,
      "dayLow": 1957.99,
      "previousClose": null,
      "intradayDropPctFromHigh": 0.11935878646863639,
      "dropPctFromPreviousClose": 0,
      "dayLowDropPctFromHigh": 1.3910083047526902,
      "reboundPctFromDayLow": 1.2895877915617546,
      "priceWarning": null,
      "priceError": null,
      "dataAgeMinutes": 0,
      "isStale": false,
      "isDataBlocked": false,
      "value": 0,
      "pnl": 0,
      "pnlPct": 0,
      "weightPct": 0
    },
    {
      "symbol": "SMH",
      "name": "VanEck Semiconductor ETF",
      "type": "watch",
      "quantity": 0.77387993,
      "cost": 650.85,
      "price": 656.98,
      "priceOk": true,
      "priceSource": "Bitget RSMHUSDT",
      "priceUpdatedAt": "2026-06-30T18:45:13.453Z",
      "priceCachedFallback": false,
      "dayHigh": 657.06,
      "dayLow": 650.91,
      "previousClose": null,
      "intradayDropPctFromHigh": 0.01217544820867611,
      "dropPctFromPreviousClose": 0,
      "dayLowDropPctFromHigh": 0.9359875810428236,
      "reboundPctFromDayLow": 0.9325405970103472,
      "priceWarning": null,
      "priceError": null,
      "dataAgeMinutes": 0,
      "isStale": false,
      "isDataBlocked": false,
      "value": 508.4236364114,
      "pnl": 4.743883970900015,
      "pnlPct": 0.9418452792502143,
      "weightPct": 3.180046091259385
    },
    {
      "symbol": "SOXX",
      "name": "iShares Semiconductor ETF",
      "type": "watch",
      "quantity": 0,
      "cost": 0,
      "price": 642.17,
      "priceOk": true,
      "priceSource": "Bitget RSOXXUSDT",
      "priceUpdatedAt": "2026-06-30T18:45:13.454Z",
      "priceCachedFallback": false,
      "dayHigh": 642.29,
      "dayLow": 635.62,
      "previousClose": null,
      "intradayDropPctFromHigh": 0.018683149356210522,
      "dropPctFromPreviousClose": 0,
      "dayLowDropPctFromHigh": 1.0384717183826557,
      "reboundPctFromDayLow": 1.0304899153582256,
      "priceWarning": null,
      "priceError": null,
      "dataAgeMinutes": 0,
      "isStale": false,
      "isDataBlocked": false,
      "value": 0,
      "pnl": 0,
      "pnlPct": 0,
      "weightPct": 0
    }
  ],
  "bitgetSync": {
    "enabled": false,
    "used": false,
    "source": "disabled-holdings-json-mode"
  },
  "holdingsSource": {
    "mode": "holdings-json-only",
    "file": "config/holdings.json",
    "note": "页面和邮件均以 holdings.json 为唯一仓位来源。"
  },
  "btcFiveMinuteChangePct": 0.042764290585749334,
  "highWatermark": 16002.0181128451,
  "drawdownPct": 0.08802125161278777,
  "btcWeeklyGainPct": -0.8728983050847492,
  "buyPauseUntil": null,
  "buyPaused": false,
  "healthSummary": {
    "score": {
      "total": 99,
      "grade": "优秀",
      "components": [
        {
          "label": "现金安全",
          "max": 20,
          "score": 20,
          "reasons": []
        },
        {
          "label": "核心仓完整度",
          "max": 25,
          "score": 24,
          "reasons": [
            "BTC/ETH 合计达标，但 ETH 偏低，仅作为结构提示。"
          ]
        },
        {
          "label": "投机仓控制",
          "max": 15,
          "score": 15,
          "reasons": []
        },
        {
          "label": "AI抽水机仓控制",
          "max": 15,
          "score": 15,
          "reasons": []
        },
        {
          "label": "数据与纪律",
          "max": 15,
          "score": 15,
          "reasons": []
        },
        {
          "label": "回撤状态",
          "max": 10,
          "score": 10,
          "reasons": []
        }
      ],
      "reasons": [
        "核心仓完整度：BTC/ETH 合计达标，但 ETH 偏低，仅作为结构提示。"
      ],
      "topAdvice": [
        "BTC/ETH 总量达标但 ETH 偏低，这是结构偏科，不是核心不足。"
      ],
      "layers": [
        {
          "id": "cash",
          "name": "安全现金层",
          "symbols": [
            "USDT",
            "USDGO"
          ],
          "value": 8004.286823179999,
          "weightPct": 50.06455090293246,
          "targetText": "成熟目标 35%-45%，阶段目标 65% / 50%",
          "status": {
            "label": "健康",
            "level": ""
          },
          "advice": "现金处于可执行区间，继续按 AI 优先规则分批。"
        },
        {
          "id": "core",
          "name": "核心增长层",
          "symbols": [
            "BTC",
            "ETH"
          ],
          "value": 1904.6358111304999,
          "weightPct": 11.912958471421662,
          "targetText": "BTC 5%-8%，ETH 3%-5%；当前阶段只做底仓，不抢 AI 主攻资金",
          "status": {
            "label": "核心偏科",
            "level": "info"
          },
          "advice": "BTC/ETH 合计已达标，但 ETH 低于单项底仓线；这只是结构提示，不影响 AI 主攻仓优先级。"
        },
        {
          "id": "stable",
          "name": "长期稳定层",
          "symbols": [
            "VOO",
            "XAUT"
          ],
          "value": 911.3516274432,
          "weightPct": 5.700246749088089,
          "targetText": "VOO 5%-7%，XAUT 3%-4%；保险底仓，不做当前主攻",
          "status": {
            "label": "健康",
            "level": ""
          },
          "advice": "稳定层已建立，当前不继续抢 AI 主攻资金。"
        },
        {
          "id": "theme",
          "name": "AI抽水机主攻仓",
          "symbols": [
            "MU",
            "DRAM",
            "GLW",
            "SMH",
            "MRVL",
            "ANET",
            "AVGO",
            "TSM",
            "ASML",
            "SOXX",
            "WDC",
            "SNDK",
            "FN",
            "AAOI",
            "ASX"
          ],
          "value": 4554.1612097981,
          "weightPct": 28.48499069871102,
          "targetText": "目标 25%-35%，35% 停止新增，40% 硬上限；MU/DRAM/GLW/SMH 单笔 500 USDT 起",
          "status": {
            "label": "健康",
            "level": ""
          },
          "advice": "AI 抽水机仓是收益主攻层，35% 后停止新增，40% 为硬上限。"
        },
        {
          "id": "speculative",
          "name": "投机清理层",
          "symbols": [
            "DOGE",
            "BGB"
          ],
          "value": 613.497464667069,
          "weightPct": 3.8372531778467707,
          "targetText": "DOGE 可作为 BTC 高弹性卫星；DOGE+BGB 目标 0%-4%，4.5% 禁止新增，5% 只减不补",
          "status": {
            "label": "健康",
            "level": ""
          },
          "advice": "DOGE 可适度作为 BTC 放大器，但仍不能摊低成本或替代核心仓。"
        }
      ]
    },
    "layers": [
      {
        "id": "cash",
        "name": "安全现金层",
        "symbols": [
          "USDT",
          "USDGO"
        ],
        "value": 8004.286823179999,
        "weightPct": 50.06455090293246,
        "targetText": "成熟目标 35%-45%，阶段目标 65% / 50%",
        "status": {
          "label": "健康",
          "level": ""
        },
        "advice": "现金处于可执行区间，继续按 AI 优先规则分批。"
      },
      {
        "id": "core",
        "name": "核心增长层",
        "symbols": [
          "BTC",
          "ETH"
        ],
        "value": 1904.6358111304999,
        "weightPct": 11.912958471421662,
        "targetText": "BTC 5%-8%，ETH 3%-5%；当前阶段只做底仓，不抢 AI 主攻资金",
        "status": {
          "label": "核心偏科",
          "level": "info"
        },
        "advice": "BTC/ETH 合计已达标，但 ETH 低于单项底仓线；这只是结构提示，不影响 AI 主攻仓优先级。"
      },
      {
        "id": "stable",
        "name": "长期稳定层",
        "symbols": [
          "VOO",
          "XAUT"
        ],
        "value": 911.3516274432,
        "weightPct": 5.700246749088089,
        "targetText": "VOO 5%-7%，XAUT 3%-4%；保险底仓，不做当前主攻",
        "status": {
          "label": "健康",
          "level": ""
        },
        "advice": "稳定层已建立，当前不继续抢 AI 主攻资金。"
      },
      {
        "id": "theme",
        "name": "AI抽水机主攻仓",
        "symbols": [
          "MU",
          "DRAM",
          "GLW",
          "SMH",
          "MRVL",
          "ANET",
          "AVGO",
          "TSM",
          "ASML",
          "SOXX",
          "WDC",
          "SNDK",
          "FN",
          "AAOI",
          "ASX"
        ],
        "value": 4554.1612097981,
        "weightPct": 28.48499069871102,
        "targetText": "目标 25%-35%，35% 停止新增，40% 硬上限；MU/DRAM/GLW/SMH 单笔 500 USDT 起",
        "status": {
          "label": "健康",
          "level": ""
        },
        "advice": "AI 抽水机仓是收益主攻层，35% 后停止新增，40% 为硬上限。"
      },
      {
        "id": "speculative",
        "name": "投机清理层",
        "symbols": [
          "DOGE",
          "BGB"
        ],
        "value": 613.497464667069,
        "weightPct": 3.8372531778467707,
        "targetText": "DOGE 可作为 BTC 高弹性卫星；DOGE+BGB 目标 0%-4%，4.5% 禁止新增，5% 只减不补",
        "status": {
          "label": "健康",
          "level": ""
        },
        "advice": "DOGE 可适度作为 BTC 放大器，但仍不能摊低成本或替代核心仓。"
      }
    ],
    "judgement": [
      "BTC/ETH 合计已达标，但 ETH 偏低，这是核心偏科，不是核心不足；不影响 AI 主攻仓优先。"
    ],
    "allowedActions": [
      "BTC/ETH 总量达标但 ETH 偏低；这是结构偏科，只提示不强制买。",
      "AI 主攻仓进入健康进攻区，后续只在急跌或深回调时继续加，不追涨。",
      "允许做月度复盘、更新持仓成本和检查价格源。"
    ],
    "forbiddenActions": [
      "不要因为刚买就跌而立刻补同一个标的。"
    ],
    "phasePlan": [
      {
        "name": "第一阶段：现金降到 60%-65%",
        "deployAmount": 0,
        "target": "新增资金优先 AI 主攻仓；BTC/XAUT 弱势阶段只保留底仓，不继续机械补仓。",
        "steps": [
          "MU/DRAM/GLW/SMH 建立有效主攻仓，单笔 500 USDT 起",
          "AI A/S 急跌机会执行 1000-2500 USDT",
          "BTC 只在 56k/55k 或趋势确认后小额补",
          "XAUT 3850 以下才补，3900 上方不补"
        ]
      },
      {
        "name": "第二阶段：现金降到 45%-50%",
        "deployAmount": 10.320355070565235,
        "target": "AI 主攻仓推进到 25%-35%，让账户真正吃到主升方向。",
        "steps": [
          "AI 抽水机仓推进到 25% 以上",
          "MU/DRAM/GLW/SMH 单项向 4%-8% 目标靠拢",
          "MRVL/ANET/AVGO 只做第二梯队",
          "不因 BTC/XAUT 目标不足而挤占 AI 弹药"
        ]
      },
      {
        "name": "第三阶段：现金稳定 35%-45%",
        "deployAmount": 809.7170018815085,
        "target": "形成趋势优先结构：现金有防守，AI 主攻仓能真正影响账户收益。",
        "steps": [
          "现金保留 35%-45%",
          "AI 抽水机仓 25%-35%",
          "AI 35% 后停止新增，40% 硬上限",
          "BTC/XAUT 只做保险底仓",
          "每月复盘再平衡"
        ]
      }
    ],
    "freshness": {
      "ageMinutes": 0,
      "isStale": false,
      "isBlocked": false,
      "missingPrices": [],
      "label": "数据新鲜"
    },
    "cooldown": {
      "configured": false,
      "status": "未配置交易记录",
      "blockedSymbols": [],
      "messages": [
        "冷却机制：未配置交易记录；页面只显示规则，不伪造最近交易。"
      ]
    },
    "rebalanceAlerts": []
  }
}
