{
  "updatedAt": "2026-06-30T13:05:14.221Z",
  "source": "github-actions",
  "totalValue": 15917.048549980653,
  "cashValue": 10989.334155120001,
  "cashPct": 69.04128061564127,
  "dataAgeMinutes": 0,
  "isStale": false,
  "isDataBlocked": false,
  "weights": {
    "USDT": 59.59407174109255,
    "USDGO": 9.447208874548716,
    "BTC": 7.909486980559158,
    "ETH": 2.491026811226771,
    "DOGE": 2.2303118123303425,
    "BGB": 0.26275550729680247,
    "VOO": 2.522234408865254,
    "XAUT": 3.171559298671698,
    "AVGO": 0,
    "FN": 0,
    "MU": 3.6550475421299575,
    "SNDK": 2.1156859411552738,
    "DRAM": 2.5068667954806543,
    "WDC": 1.3234029907966576,
    "ASX": 0,
    "AAOI": 0,
    "GLW": 1.3973998036330066,
    "MRVL": 1.3729414922131755,
    "ANET": 0,
    "TSM": 0,
    "ASML": 0,
    "SMH": 0,
    "SOXX": 0
  },
  "priceErrors": {},
  "priceWarnings": {},
  "positions": [
    {
      "symbol": "USDT",
      "name": "Tether",
      "type": "cash",
      "quantity": 9485.61733194,
      "cost": 1,
      "price": 1,
      "priceOk": true,
      "priceSource": "Fixed 1 USDT",
      "priceUpdatedAt": "2026-06-30T13:05:13.642Z",
      "priceCachedFallback": false,
      "dayHigh": null,
      "dayLow": null,
      "previousClose": null,
      "intradayDropPctFromHigh": 0,
      "dropPctFromPreviousClose": 0,
      "dayLowDropPctFromHigh": 0,
      "reboundPctFromDayLow": 0,
      "priceWarning": null,
      "priceError": null,
      "dataAgeMinutes": 0,
      "isStale": false,
      "isDataBlocked": false,
      "value": 9485.61733194,
      "pnl": 0,
      "pnlPct": 0,
      "weightPct": 59.59407174109255
    },
    {
      "symbol": "USDGO",
      "name": "USDGO",
      "type": "cash",
      "quantity": 1503.71682318,
      "cost": 1.0019,
      "price": 1,
      "priceOk": true,
      "priceSource": "Fixed 1 USDT",
      "priceUpdatedAt": "2026-06-30T13:05:13.642Z",
      "priceCachedFallback": false,
      "dayHigh": null,
      "dayLow": null,
      "previousClose": null,
      "intradayDropPctFromHigh": 0,
      "dropPctFromPreviousClose": 0,
      "dayLowDropPctFromHigh": 0,
      "reboundPctFromDayLow": 0,
      "priceWarning": null,
      "priceError": null,
      "dataAgeMinutes": 0,
      "isStale": false,
      "isDataBlocked": false,
      "value": 1503.71682318,
      "pnl": -2.857061964042032,
      "pnlPct": -0.1896396845992635,
      "weightPct": 9.447208874548716
    },
    {
      "symbol": "BTC",
      "name": "Bitcoin",
      "type": "crypto",
      "quantity": 0.02152615,
      "cost": 59652.38,
      "price": 58485,
      "priceOk": true,
      "priceSource": "Bitget BTCUSDT",
      "priceUpdatedAt": "2026-06-30T13:05:13.642Z",
      "priceCachedFallback": false,
      "dayHigh": 60683.9,
      "dayLow": 58323.97,
      "previousClose": 60258.1,
      "intradayDropPctFromHigh": 3.6235311178088447,
      "dropPctFromPreviousClose": 2.942508973897283,
      "dayLowDropPctFromHigh": 3.888889804379745,
      "reboundPctFromDayLow": 0.2760957458828657,
      "priceWarning": null,
      "priceError": null,
      "dataAgeMinutes": 0,
      "isStale": false,
      "isDataBlocked": false,
      "value": 1258.95688275,
      "pnl": -25.129196987000114,
      "pnlPct": -1.9569713731455562,
      "weightPct": 7.909486980559158
    },
    {
      "symbol": "ETH",
      "name": "Ethereum",
      "type": "crypto",
      "quantity": 0.2546747,
      "cost": 1570.39,
      "price": 1556.88,
      "priceOk": true,
      "priceSource": "Bitget ETHUSDT",
      "priceUpdatedAt": "2026-06-30T13:05:13.705Z",
      "priceCachedFallback": false,
      "dayHigh": 1637.59,
      "dayLow": 1551.01,
      "previousClose": 1613.02,
      "intradayDropPctFromHigh": 4.928584077821665,
      "dropPctFromPreviousClose": 3.48042801701156,
      "dayLowDropPctFromHigh": 5.287037658998891,
      "reboundPctFromDayLow": 0.37846306600216106,
      "priceWarning": null,
      "priceError": null,
      "dataAgeMinutes": 0,
      "isStale": false,
      "isDataBlocked": false,
      "value": 396.497946936,
      "pnl": -3.4406551969999555,
      "pnlPct": -0.8602958500754478,
      "weightPct": 2.491026811226771
    },
    {
      "symbol": "DOGE",
      "name": "Dogecoin",
      "type": "crypto",
      "quantity": 5073.6003142,
      "cost": 0.07489,
      "price": 0.06997,
      "priceOk": true,
      "priceSource": "Bitget DOGEUSDT",
      "priceUpdatedAt": "2026-06-30T13:05:13.706Z",
      "priceCachedFallback": false,
      "dayHigh": 0.07427,
      "dayLow": 0.06952,
      "previousClose": 0.07347,
      "intradayDropPctFromHigh": 5.7896862797899535,
      "dropPctFromPreviousClose": 4.763849190145623,
      "dayLowDropPctFromHigh": 6.395583681163329,
      "reboundPctFromDayLow": 0.6472957422324597,
      "priceWarning": null,
      "priceError": null,
      "dataAgeMinutes": 0,
      "isStale": false,
      "isDataBlocked": false,
      "value": 354.999813984574,
      "pnl": -24.962113545863986,
      "pnlPct": -6.569635465349174,
      "weightPct": 2.2303118123303425
    },
    {
      "symbol": "BGB",
      "name": "Bitget Token",
      "type": "crypto",
      "quantity": 25.91259087,
      "cost": 1.978,
      "price": 1.614,
      "priceOk": true,
      "priceSource": "Bitget BGBUSDT",
      "priceUpdatedAt": "2026-06-30T13:05:13.707Z",
      "priceCachedFallback": false,
      "dayHigh": 1.6358,
      "dayLow": 1.605,
      "previousClose": 1.624,
      "intradayDropPctFromHigh": 1.3326812568773578,
      "dropPctFromPreviousClose": 0.61576354679803,
      "dayLowDropPctFromHigh": 1.88287076659738,
      "reboundPctFromDayLow": 0.5607476635514093,
      "priceWarning": null,
      "priceError": null,
      "dataAgeMinutes": 0,
      "isStale": false,
      "isDataBlocked": false,
      "value": 41.82292166418,
      "pnl": -9.432183076679998,
      "pnlPct": -18.402426693629927,
      "weightPct": 0.26275550729680247
    },
    {
      "symbol": "VOO",
      "name": "Vanguard S&P 500 ETF",
      "type": "watch",
      "quantity": 0.58957511,
      "cost": 677.85,
      "price": 680.94,
      "priceOk": true,
      "priceSource": "Bitget RVOOUSDT",
      "priceUpdatedAt": "2026-06-30T13:05:13.708Z",
      "priceCachedFallback": false,
      "dayHigh": 682.92,
      "dayLow": 678.31,
      "previousClose": null,
      "intradayDropPctFromHigh": 0.2899314707432649,
      "dropPctFromPreviousClose": 0,
      "dayLowDropPctFromHigh": 0.6750424647103634,
      "reboundPctFromDayLow": 0.38772832480725766,
      "priceWarning": null,
      "priceError": null,
      "dataAgeMinutes": 0,
      "isStale": false,
      "isDataBlocked": false,
      "value": 401.4652754034,
      "pnl": 1.821787089900056,
      "pnlPct": 0.4558530648373674,
      "weightPct": 2.522234408865254
    },
    {
      "symbol": "XAUT",
      "name": "Tether Gold",
      "type": "watch",
      "quantity": 0.1258369,
      "cost": 3974.69,
      "price": 4011.69,
      "priceOk": true,
      "priceSource": "Bitget XAUTUSDT",
      "priceUpdatedAt": "2026-06-30T13:05:13.709Z",
      "priceCachedFallback": false,
      "dayHigh": 4045.35,
      "dayLow": 3943.88,
      "previousClose": 4011.52,
      "intradayDropPctFromHigh": 0.8320664466609775,
      "dropPctFromPreviousClose": -0.004237795149969905,
      "dayLowDropPctFromHigh": 2.508312012557623,
      "reboundPctFromDayLow": 1.7193728003894626,
      "priceWarning": null,
      "priceError": null,
      "dataAgeMinutes": 0,
      "isStale": false,
      "isDataBlocked": false,
      "value": 504.818633361,
      "pnl": 4.655965299999991,
      "pnlPct": 0.930890207789788,
      "weightPct": 3.171559298671698
    },
    {
      "symbol": "AVGO",
      "name": "Broadcom",
      "type": "watch",
      "quantity": 0,
      "cost": 0,
      "price": 375.13,
      "priceOk": true,
      "priceSource": "Bitget RAVGOUSDT",
      "priceUpdatedAt": "2026-06-30T13:05:13.710Z",
      "priceCachedFallback": false,
      "dayHigh": 378.03,
      "dayLow": 369.93,
      "previousClose": null,
      "intradayDropPctFromHigh": 0.7671348834748505,
      "dropPctFromPreviousClose": 0,
      "dayLowDropPctFromHigh": 2.1426870883263143,
      "reboundPctFromDayLow": 1.405671343227094,
      "priceWarning": null,
      "priceError": null,
      "dataAgeMinutes": 0,
      "isStale": false,
      "isDataBlocked": false,
      "value": 0,
      "pnl": 0,
      "pnlPct": 0,
      "weightPct": 0
    },
    {
      "symbol": "FN",
      "name": "Fabrinet",
      "type": "watch",
      "quantity": 0,
      "cost": 0,
      "price": 528.89,
      "priceOk": true,
      "priceSource": "Bitget RFNUSDT",
      "priceUpdatedAt": "2026-06-30T13:05:13.711Z",
      "priceCachedFallback": false,
      "dayHigh": 538,
      "dayLow": 524.15,
      "previousClose": null,
      "intradayDropPctFromHigh": 1.693308550185876,
      "dropPctFromPreviousClose": 0,
      "dayLowDropPctFromHigh": 2.5743494423791864,
      "reboundPctFromDayLow": 0.9043212820757435,
      "priceWarning": null,
      "priceError": null,
      "dataAgeMinutes": 0,
      "isStale": false,
      "isDataBlocked": false,
      "value": 0,
      "pnl": 0,
      "pnlPct": 0,
      "weightPct": 0
    },
    {
      "symbol": "MU",
      "name": "Micron",
      "type": "watch",
      "quantity": 0.51167157,
      "cost": 1102.51,
      "price": 1137.01,
      "priceOk": true,
      "priceSource": "Bitget RMUUSDT",
      "priceUpdatedAt": "2026-06-30T13:05:13.712Z",
      "priceCachedFallback": false,
      "dayHigh": 1164,
      "dayLow": 1093.06,
      "previousClose": null,
      "intradayDropPctFromHigh": 2.3187285223367704,
      "dropPctFromPreviousClose": 0,
      "dayLowDropPctFromHigh": 6.094501718213063,
      "reboundPctFromDayLow": 4.020822278740422,
      "priceWarning": null,
      "priceError": null,
      "dataAgeMinutes": 0,
      "isStale": false,
      "isDataBlocked": false,
      "value": 581.7756918056999,
      "pnl": 17.65266916500002,
      "pnlPct": 3.129223317702338,
      "weightPct": 3.6550475421299575
    },
    {
      "symbol": "SNDK",
      "name": "SanDisk",
      "type": "watch",
      "quantity": 0.16168057,
      "cost": 1969.15,
      "price": 2082.84,
      "priceOk": true,
      "priceSource": "Bitget RSNDKUSDT",
      "priceUpdatedAt": "2026-06-30T13:05:13.713Z",
      "priceCachedFallback": false,
      "dayHigh": 2125.87,
      "dayLow": 1976.99,
      "previousClose": null,
      "intradayDropPctFromHigh": 2.0241124810077635,
      "dropPctFromPreviousClose": 0,
      "dayLowDropPctFromHigh": 7.003250433939982,
      "reboundPctFromDayLow": 5.354098907935808,
      "priceWarning": null,
      "priceError": null,
      "dataAgeMinutes": 0,
      "isStale": false,
      "isDataBlocked": false,
      "value": 336.7547584188,
      "pnl": 18.381464003299982,
      "pnlPct": 5.7735571185536845,
      "weightPct": 2.1156859411552738
    },
    {
      "symbol": "DRAM",
      "name": "Roundhill Memory ETF",
      "type": "watch",
      "quantity": 5.5535032,
      "cost": 69.52,
      "price": 71.85,
      "priceOk": true,
      "priceSource": "Bitget RDRAMUSDT",
      "priceUpdatedAt": "2026-06-30T13:05:13.714Z",
      "priceCachedFallback": false,
      "dayHigh": 73.93,
      "dayLow": 69.65,
      "previousClose": null,
      "intradayDropPctFromHigh": 2.813472203435699,
      "dropPctFromPreviousClose": 0,
      "dayLowDropPctFromHigh": 5.789260110915732,
      "reboundPctFromDayLow": 3.1586503948312825,
      "priceWarning": null,
      "priceError": null,
      "dataAgeMinutes": 0,
      "isStale": false,
      "isDataBlocked": false,
      "value": 399.01920491999994,
      "pnl": 12.939662455999951,
      "pnlPct": 3.351553509781345,
      "weightPct": 2.5068667954806543
    },
    {
      "symbol": "WDC",
      "name": "Western Digital",
      "type": "watch",
      "quantity": 0.3305247,
      "cost": 604.3,
      "price": 637.31,
      "priceOk": true,
      "priceSource": "Bitget RWDCUSDT",
      "priceUpdatedAt": "2026-06-30T13:05:13.715Z",
      "priceCachedFallback": false,
      "dayHigh": 669.51,
      "dayLow": 633,
      "previousClose": null,
      "intradayDropPctFromHigh": 4.809487535660415,
      "dropPctFromPreviousClose": 0,
      "dayLowDropPctFromHigh": 5.453241923197561,
      "reboundPctFromDayLow": 0.6808846761453311,
      "priceWarning": null,
      "priceError": null,
      "dataAgeMinutes": 0,
      "isStale": false,
      "isDataBlocked": false,
      "value": 210.64669655699998,
      "pnl": 10.910620346999991,
      "pnlPct": 5.462518616581164,
      "weightPct": 1.3234029907966576
    },
    {
      "symbol": "ASX",
      "name": "ASE Technology",
      "type": "watch",
      "quantity": 0,
      "cost": 0,
      "price": 42.1,
      "priceOk": true,
      "priceSource": "Bitget RASXUSDT",
      "priceUpdatedAt": "2026-06-30T13:05:13.716Z",
      "priceCachedFallback": false,
      "dayHigh": 43.24,
      "dayLow": 40.74,
      "previousClose": null,
      "intradayDropPctFromHigh": 2.63644773358002,
      "dropPctFromPreviousClose": 0,
      "dayLowDropPctFromHigh": 5.78168362627197,
      "reboundPctFromDayLow": 3.338242513500244,
      "priceWarning": null,
      "priceError": null,
      "dataAgeMinutes": 0,
      "isStale": false,
      "isDataBlocked": false,
      "value": 0,
      "pnl": 0,
      "pnlPct": 0,
      "weightPct": 0
    },
    {
      "symbol": "AAOI",
      "name": "Applied Optoelectronics",
      "type": "watch",
      "quantity": 0,
      "cost": 0,
      "price": 144.63,
      "priceOk": true,
      "priceSource": "Bitget RAAOIUSDT",
      "priceUpdatedAt": "2026-06-30T13:05:13.716Z",
      "priceCachedFallback": false,
      "dayHigh": 152.38,
      "dayLow": 141.78,
      "previousClose": null,
      "intradayDropPctFromHigh": 5.085969287308046,
      "dropPctFromPreviousClose": 0,
      "dayLowDropPctFromHigh": 6.956293476834227,
      "reboundPctFromDayLow": 2.0101565806178545,
      "priceWarning": null,
      "priceError": null,
      "dataAgeMinutes": 0,
      "isStale": false,
      "isDataBlocked": false,
      "value": 0,
      "pnl": 0,
      "pnlPct": 0,
      "weightPct": 0
    },
    {
      "symbol": "GLW",
      "name": "Corning",
      "type": "watch",
      "quantity": 0.88859736,
      "cost": 243.1,
      "price": 250.31,
      "priceOk": true,
      "priceSource": "Bitget RGLWUSDT",
      "priceUpdatedAt": "2026-06-30T13:05:13.717Z",
      "priceCachedFallback": false,
      "dayHigh": 265.71,
      "dayLow": 246.44,
      "previousClose": null,
      "intradayDropPctFromHigh": 5.79579240525384,
      "dropPctFromPreviousClose": 0,
      "dayLowDropPctFromHigh": 7.25226750969101,
      "reboundPctFromDayLow": 1.5703619542282117,
      "priceWarning": null,
      "priceError": null,
      "dataAgeMinutes": 0,
      "isStale": false,
      "isDataBlocked": false,
      "value": 222.4248051816,
      "pnl": 6.406786965599991,
      "pnlPct": 2.9658576717400207,
      "weightPct": 1.3973998036330066
    },
    {
      "symbol": "MRVL",
      "name": "Marvell Technology",
      "type": "watch",
      "quantity": 0.79587648,
      "cost": 251.95,
      "price": 274.58,
      "priceOk": true,
      "priceSource": "Bitget RMRVLUSDT",
      "priceUpdatedAt": "2026-06-30T13:05:13.718Z",
      "priceCachedFallback": false,
      "dayHigh": 282.91,
      "dayLow": 268.21,
      "previousClose": null,
      "intradayDropPctFromHigh": 2.94439927892264,
      "dropPctFromPreviousClose": 0,
      "dayLowDropPctFromHigh": 5.195998727510531,
      "reboundPctFromDayLow": 2.3750046605272006,
      "priceWarning": null,
      "priceError": null,
      "dataAgeMinutes": 0,
      "isStale": false,
      "isDataBlocked": false,
      "value": 218.5317638784,
      "pnl": 18.010684742400002,
      "pnlPct": 8.981940861282002,
      "weightPct": 1.3729414922131755
    },
    {
      "symbol": "ANET",
      "name": "Arista Networks",
      "type": "watch",
      "quantity": 0,
      "cost": 0,
      "price": 164.11,
      "priceOk": true,
      "priceSource": "Bitget RANETUSDT",
      "priceUpdatedAt": "2026-06-30T13:05:13.719Z",
      "priceCachedFallback": false,
      "dayHigh": 165.6,
      "dayLow": 162.51,
      "previousClose": null,
      "intradayDropPctFromHigh": 0.8997584541062685,
      "dropPctFromPreviousClose": 0,
      "dayLowDropPctFromHigh": 1.8659420289855095,
      "reboundPctFromDayLow": 0.9845547966279138,
      "priceWarning": null,
      "priceError": null,
      "dataAgeMinutes": 0,
      "isStale": false,
      "isDataBlocked": false,
      "value": 0,
      "pnl": 0,
      "pnlPct": 0,
      "weightPct": 0
    },
    {
      "symbol": "TSM",
      "name": "Taiwan Semiconductor Manufacturing",
      "type": "watch",
      "quantity": 0,
      "cost": 0,
      "price": 452.32,
      "priceOk": true,
      "priceSource": "Bitget RTSMUSDT",
      "priceUpdatedAt": "2026-06-30T13:05:13.720Z",
      "priceCachedFallback": false,
      "dayHigh": 456.08,
      "dayLow": 447.64,
      "previousClose": null,
      "intradayDropPctFromHigh": 0.824416768987895,
      "dropPctFromPreviousClose": 0,
      "dayLowDropPctFromHigh": 1.8505525346430445,
      "reboundPctFromDayLow": 1.0454829773925491,
      "priceWarning": null,
      "priceError": null,
      "dataAgeMinutes": 0,
      "isStale": false,
      "isDataBlocked": false,
      "value": 0,
      "pnl": 0,
      "pnlPct": 0,
      "weightPct": 0
    },
    {
      "symbol": "ASML",
      "name": "ASML Holding",
      "type": "watch",
      "quantity": 0,
      "cost": 0,
      "price": 1905.38,
      "priceOk": true,
      "priceSource": "Bitget RASMLUSDT",
      "priceUpdatedAt": "2026-06-30T13:05:13.720Z",
      "priceCachedFallback": false,
      "dayHigh": 1913.58,
      "dayLow": 1853.26,
      "previousClose": null,
      "intradayDropPctFromHigh": 0.4285161843246595,
      "dropPctFromPreviousClose": 0,
      "dayLowDropPctFromHigh": 3.1522068583492686,
      "reboundPctFromDayLow": 2.812341495526808,
      "priceWarning": null,
      "priceError": null,
      "dataAgeMinutes": 0,
      "isStale": false,
      "isDataBlocked": false,
      "value": 0,
      "pnl": 0,
      "pnlPct": 0,
      "weightPct": 0
    },
    {
      "symbol": "SMH",
      "name": "VanEck Semiconductor ETF",
      "type": "watch",
      "quantity": 0,
      "cost": 0,
      "price": 633.44,
      "priceOk": true,
      "priceSource": "Bitget RSMHUSDT",
      "priceUpdatedAt": "2026-06-30T13:05:13.721Z",
      "priceCachedFallback": false,
      "dayHigh": 639.39,
      "dayLow": 624.23,
      "previousClose": null,
      "intradayDropPctFromHigh": 0.9305744537762448,
      "dropPctFromPreviousClose": 0,
      "dayLowDropPctFromHigh": 2.371009868781177,
      "reboundPctFromDayLow": 1.475417714624423,
      "priceWarning": null,
      "priceError": null,
      "dataAgeMinutes": 0,
      "isStale": false,
      "isDataBlocked": false,
      "value": 0,
      "pnl": 0,
      "pnlPct": 0,
      "weightPct": 0
    },
    {
      "symbol": "SOXX",
      "name": "iShares Semiconductor ETF",
      "type": "watch",
      "quantity": 0,
      "cost": 0,
      "price": 614.38,
      "priceOk": true,
      "priceSource": "Bitget RSOXXUSDT",
      "priceUpdatedAt": "2026-06-30T13:05:13.722Z",
      "priceCachedFallback": false,
      "dayHigh": 622.01,
      "dayLow": 603.83,
      "previousClose": null,
      "intradayDropPctFromHigh": 1.2266683815372736,
      "dropPctFromPreviousClose": 0,
      "dayLowDropPctFromHigh": 2.922782591919736,
      "reboundPctFromDayLow": 1.7471804978222272,
      "priceWarning": null,
      "priceError": null,
      "dataAgeMinutes": 0,
      "isStale": false,
      "isDataBlocked": false,
      "value": 0,
      "pnl": 0,
      "pnlPct": 0,
      "weightPct": 0
    }
  ],
  "bitgetSync": {
    "enabled": false,
    "used": false,
    "source": "disabled-holdings-json-mode"
  },
  "holdingsSource": {
    "mode": "holdings-json-only",
    "file": "config/holdings.json",
    "note": "页面和邮件均以 holdings.json 为唯一仓位来源。"
  },
  "btcFiveMinuteChangePct": 0.029315331370995297,
  "highWatermark": 15983.287425472516,
  "drawdownPct": 0.4144258545103696,
  "btcWeeklyGainPct": -0.8728813559322033,
  "buyPauseUntil": null,
  "buyPaused": false,
  "healthSummary": {
    "score": {
      "total": 99,
      "grade": "优秀",
      "components": [
        {
          "label": "现金安全",
          "max": 20,
          "score": 20,
          "reasons": []
        },
        {
          "label": "核心仓完整度",
          "max": 25,
          "score": 24,
          "reasons": [
            "BTC/ETH 合计达标，但 ETH 偏低，仅作为结构提示。"
          ]
        },
        {
          "label": "投机仓控制",
          "max": 15,
          "score": 15,
          "reasons": []
        },
        {
          "label": "AI抽水机仓控制",
          "max": 15,
          "score": 15,
          "reasons": []
        },
        {
          "label": "数据与纪律",
          "max": 15,
          "score": 15,
          "reasons": []
        },
        {
          "label": "回撤状态",
          "max": 10,
          "score": 10,
          "reasons": []
        }
      ],
      "reasons": [
        "核心仓完整度：BTC/ETH 合计达标，但 ETH 偏低，仅作为结构提示。"
      ],
      "topAdvice": [
        "现金偏高且 AI 主攻仓不足，新增资金优先 MU/DRAM/GLW/SMH；BTC/XAUT 暂不机械补仓。",
        "BTC/ETH 总量达标但 ETH 偏低，这是结构偏科，不是核心不足。"
      ],
      "layers": [
        {
          "id": "cash",
          "name": "安全现金层",
          "symbols": [
            "USDT",
            "USDGO"
          ],
          "value": 10989.334155120001,
          "weightPct": 69.04128061564127,
          "targetText": "成熟目标 35%-45%，阶段目标 65% / 50%",
          "status": {
            "label": "健康",
            "level": ""
          },
          "advice": "现金安全但资金效率偏低，新增资金优先给 AI 主攻仓。"
        },
        {
          "id": "core",
          "name": "核心增长层",
          "symbols": [
            "BTC",
            "ETH"
          ],
          "value": 1655.454829686,
          "weightPct": 10.40051379178593,
          "targetText": "BTC 5%-8%，ETH 3%-5%；当前阶段只做底仓，不抢 AI 主攻资金",
          "status": {
            "label": "核心偏科",
            "level": "info"
          },
          "advice": "BTC/ETH 合计已达标，但 ETH 低于单项底仓线；这只是结构提示，不影响 AI 主攻仓优先级。"
        },
        {
          "id": "stable",
          "name": "长期稳定层",
          "symbols": [
            "VOO",
            "XAUT"
          ],
          "value": 906.2839087644,
          "weightPct": 5.693793707536952,
          "targetText": "VOO 5%-7%，XAUT 3%-4%；保险底仓，不做当前主攻",
          "status": {
            "label": "健康",
            "level": ""
          },
          "advice": "稳定层已建立，当前不继续抢 AI 主攻资金。"
        },
        {
          "id": "theme",
          "name": "AI抽水机主攻仓",
          "symbols": [
            "MU",
            "DRAM",
            "GLW",
            "SMH",
            "MRVL",
            "ANET",
            "AVGO",
            "TSM",
            "ASML",
            "SOXX",
            "WDC",
            "SNDK",
            "FN",
            "AAOI",
            "ASX"
          ],
          "value": 1969.1529207615,
          "weightPct": 12.371344565408725,
          "targetText": "目标 25%-35%，35% 停止新增，40% 硬上限；MU/DRAM/GLW/SMH 单笔 500 USDT 起",
          "status": {
            "label": "待推进",
            "level": "info"
          },
          "advice": "当前阶段 AI 主攻仓优先推进到 25% 以上，BTC/XAUT 不抢新增资金。"
        },
        {
          "id": "speculative",
          "name": "投机清理层",
          "symbols": [
            "DOGE",
            "BGB"
          ],
          "value": 396.822735648754,
          "weightPct": 2.493067319627145,
          "targetText": "DOGE 可作为 BTC 高弹性卫星；DOGE+BGB 目标 0%-4%，4.5% 禁止新增，5% 只减不补",
          "status": {
            "label": "健康",
            "level": ""
          },
          "advice": "DOGE 可适度作为 BTC 放大器，但仍不能摊低成本或替代核心仓。"
        }
      ]
    },
    "layers": [
      {
        "id": "cash",
        "name": "安全现金层",
        "symbols": [
          "USDT",
          "USDGO"
        ],
        "value": 10989.334155120001,
        "weightPct": 69.04128061564127,
        "targetText": "成熟目标 35%-45%，阶段目标 65% / 50%",
        "status": {
          "label": "健康",
          "level": ""
        },
        "advice": "现金安全但资金效率偏低，新增资金优先给 AI 主攻仓。"
      },
      {
        "id": "core",
        "name": "核心增长层",
        "symbols": [
          "BTC",
          "ETH"
        ],
        "value": 1655.454829686,
        "weightPct": 10.40051379178593,
        "targetText": "BTC 5%-8%，ETH 3%-5%；当前阶段只做底仓，不抢 AI 主攻资金",
        "status": {
          "label": "核心偏科",
          "level": "info"
        },
        "advice": "BTC/ETH 合计已达标，但 ETH 低于单项底仓线；这只是结构提示，不影响 AI 主攻仓优先级。"
      },
      {
        "id": "stable",
        "name": "长期稳定层",
        "symbols": [
          "VOO",
          "XAUT"
        ],
        "value": 906.2839087644,
        "weightPct": 5.693793707536952,
        "targetText": "VOO 5%-7%，XAUT 3%-4%；保险底仓，不做当前主攻",
        "status": {
          "label": "健康",
          "level": ""
        },
        "advice": "稳定层已建立，当前不继续抢 AI 主攻资金。"
      },
      {
        "id": "theme",
        "name": "AI抽水机主攻仓",
        "symbols": [
          "MU",
          "DRAM",
          "GLW",
          "SMH",
          "MRVL",
          "ANET",
          "AVGO",
          "TSM",
          "ASML",
          "SOXX",
          "WDC",
          "SNDK",
          "FN",
          "AAOI",
          "ASX"
        ],
        "value": 1969.1529207615,
        "weightPct": 12.371344565408725,
        "targetText": "目标 25%-35%，35% 停止新增，40% 硬上限；MU/DRAM/GLW/SMH 单笔 500 USDT 起",
        "status": {
          "label": "待推进",
          "level": "info"
        },
        "advice": "当前阶段 AI 主攻仓优先推进到 25% 以上，BTC/XAUT 不抢新增资金。"
      },
      {
        "id": "speculative",
        "name": "投机清理层",
        "symbols": [
          "DOGE",
          "BGB"
        ],
        "value": 396.822735648754,
        "weightPct": 2.493067319627145,
        "targetText": "DOGE 可作为 BTC 高弹性卫星；DOGE+BGB 目标 0%-4%，4.5% 禁止新增，5% 只减不补",
        "status": {
          "label": "健康",
          "level": ""
        },
        "advice": "DOGE 可适度作为 BTC 放大器，但仍不能摊低成本或替代核心仓。"
      }
    ],
    "judgement": [
      "当前现金仍偏高，AI 主攻仓未达 25%；新增资金优先给 MU/DRAM/GLW/SMH，BTC/XAUT 只保留底仓。",
      "BTC/ETH 合计已达标，但 ETH 偏低，这是核心偏科，不是核心不足；不影响 AI 主攻仓优先。"
    ],
    "allowedActions": [
      "新增资金第一优先给 AI 主攻仓：MU/DRAM/GLW/SMH 或 SMH，单笔 500 USDT 起；A/S 急跌执行 1000-2500 USDT。",
      "BTC/ETH 总量达标但 ETH 偏低；这是结构偏科，只提示不强制买。",
      "允许做月度复盘、更新持仓成本和检查价格源。"
    ],
    "forbiddenActions": [
      "不要把新增资金继续分散到 BTC/XAUT 或杂票；AI 主攻仓未达 25% 前，优先等 MU/DRAM/GLW/SMH 的有效买点。",
      "不要因为刚买就跌而立刻补同一个标的。"
    ],
    "phasePlan": [
      {
        "name": "第一阶段：现金降到 60%-65%",
        "deployAmount": 643.2525976325768,
        "target": "新增资金优先 AI 主攻仓；BTC/XAUT 弱势阶段只保留底仓，不继续机械补仓。",
        "steps": [
          "MU/DRAM/GLW/SMH 建立有效主攻仓，单笔 500 USDT 起",
          "AI A/S 急跌机会执行 1000-2500 USDT",
          "BTC 只在 56k/55k 或趋势确认后小额补",
          "XAUT 3850 以下才补，3900 上方不补"
        ]
      },
      {
        "name": "第二阶段：现金降到 45%-50%",
        "deployAmount": 3030.809880129675,
        "target": "AI 主攻仓推进到 25%-35%，让账户真正吃到主升方向。",
        "steps": [
          "AI 抽水机仓推进到 25% 以上",
          "MU/DRAM/GLW/SMH 单项向 4%-8% 目标靠拢",
          "MRVL/ANET/AVGO 只做第二梯队",
          "不因 BTC/XAUT 目标不足而挤占 AI 弹药"
        ]
      },
      {
        "name": "第三阶段：现金稳定 35%-45%",
        "deployAmount": 3826.6623076287074,
        "target": "形成趋势优先结构：现金有防守，AI 主攻仓能真正影响账户收益。",
        "steps": [
          "现金保留 35%-45%",
          "AI 抽水机仓 25%-35%",
          "AI 35% 后停止新增，40% 硬上限",
          "BTC/XAUT 只做保险底仓",
          "每月复盘再平衡"
        ]
      }
    ],
    "freshness": {
      "ageMinutes": 0,
      "isStale": false,
      "isBlocked": false,
      "missingPrices": [],
      "label": "数据新鲜"
    },
    "cooldown": {
      "configured": false,
      "status": "未配置交易记录",
      "blockedSymbols": [],
      "messages": [
        "冷却机制：未配置交易记录；页面只显示规则，不伪造最近交易。"
      ]
    },
    "rebalanceAlerts": []
  }
}
